Workbook

Sheet UPAg_crops
A1: State | B1: Crop | C1: Season | D1: Year | E1: Area (lakh ha) | F1: Production (lakh t)
A2: Bihar | B2: Maize | C2: Kharif | D2: 2016-17 | E2: 2.41 | F2: 6.24
A3: Bihar | B3: Maize | C3: Kharif | D3: 2017-18 | E3: 2.23 | F3: 5.36
A4: Bihar | B4: Maize | C4: Kharif | D4: 2018-19 | E4: 2.23 | F4: 4.64
A5: Bihar | B5: Maize | C5: Kharif | D5: 2019-20 | E5: 2.09 | F5: 4.35
A6: Bihar | B6: Maize | C6: Kharif | D6: 2020-21 | E6: 1.94 | F6: 2.25
A7: Bihar | B7: Maize | C7: Kharif | D7: 2021-22 | E7: 1.74 | F7: 2.35
A8: Bihar | B8: Maize | C8: Kharif | D8: 2022-23 | E8: 1.81 | F8: 4.45
A9: Bihar | B9: Maize | C9: Kharif | D9: 2023-24 | E9: 2.16 | F9: 5.86
A10: Bihar | B10: Maize | C10: Kharif | D10: 2024-25 | E10: 1.93 | F10: 5.71
A11: Bihar | B11: Maize | C11: Kharif | D11: 2025-26 | E11: 2 | F11: 6.78
A12: Bihar | B12: Maize | C12: Rabi | D12: 2016-17 | E12: 4.79 | F12: 20.66
A13: Bihar | B13: Maize | C13: Rabi | D13: 2017-18 | E13: 4.54 | F13: 18.19
... A21: Bihar | B21: Maize | C21: Rabi | D21: 2025-26 | E21: 5.25 | F21: 39.28
A22: Bihar | B22: Maize | C22: Summer | D22: 2016-17
A23: Bihar | B23: Maize | C23: Summer | D23: 2017-18
A24: Bihar | B24: Maize | C24: Summer | D24: 2018-19
A25: Bihar | B25: Maize | C25: Summer | D25: 2019-20
A26: Bihar | B26: Maize | C26: Summer | D26: 2020-21
A27: Bihar | B27: Maize | C27: Summer | D27: 2021-22
A28: Bihar | B28: Maize | C28: Summer | D28: 2022-23 | E28: 1.58 | F28: 10.19
A29: Bihar | B29: Maize | C29: Summer | D29: 2023-24 | E29: 1.82 | F29: 10.72
A30: Bihar | B30: Maize | C30: Summer | D30: 2024-25 | E30: 1.54 | F30: 8.27
A31: Bihar | B31: Maize | C31: Summer | D31: 2025-26 | E31: 1.64 | F31: 9.72
A32: Bihar | B32: Maize | C32: Total | D32: 2016-17 | E32: 7.21 | F32: 26.9
A33: Bihar | B33: Maize | C33: Total | D33: 2017-18 | E33: 6.77 | F33: 23.55
A34: Bihar | B34: Maize | C34: Total | D34: 2018-19 | E34: 6.69 | F34: 24.83
A35: Bihar | B35: Maize | C35: Total | D35: 2019-20 | E35: 6.73 | F35: 20.03
A36: Bihar | B36: Maize | C36: Total | D36: 2020-21 | E36: 6.49 | F36: 20.84
A37: Bihar | B37: Maize | C37: Total | D37: 2021-22 | E37: 6.63 | F37: 26.69
A38: Bihar | B38: Maize | C38: Total | D38: 2022-23 | E38: 7.48 | F38: 43.8
A39: Bihar | B39: Maize | C39: Total | D39: 2023-24 | E39: 9.55 | F39: 57.09
... A191: Karnataka | B191: Maize | C191: Rabi | D191: 2025-26 | E191: 1.59 | F191: 5.81
A192: Karnataka | B192: Maize | C192: Summer | D192: 2016-17
A193: Karnataka | B193: Maize | C193: Summer | D193: 2017-18
A194: Karnataka | B194: Maize | C194: Summer | D194: 2018-19
A195: Karnataka | B195: Maize | C195: Summer | D195: 2019-20
A196: Karnataka | B196: Maize | C196: Summer | D196: 2020-21
A197: Karnataka | B197: Maize | C197: Summer | D197: 2021-22
A198: Karnataka | B198: Maize | C198: Summer | D198: 2022-23 | E198: 0.71 | F198: 2.67
A199: Karnataka | B199: Maize | C199: Summer | D199: 2023-24 | E199: 0.35 | F199: 1.3
A200: Karnataka | B200: Maize | C200: Summer | D200: 2024-25 | E200: 0.61 | F200: 2.64
A201: Karnataka | B201: Maize | C201: Summer | D201: 2025-26 | E201: 0.63 | F201: 2.48
A202: Karnataka | B202: Maize | C202: Total | D202: 2016-17 | E202: 13.7 | F202: 33.14
A203: Karnataka | B203: Maize | C203: Total | D203: 2017-18 | E203: 13.07 | F203: 38.54
A204: Karnataka | B204: Maize | C204: Total | D204: 2018-19 | E204: 13.4 | F204: 37.58
A205: Karnataka | B205: Maize | C205: Total | D205: 2019-20 | E205: 14.24 | F205: 42.58
A206: Karnataka | B206: Maize | C206: Total | D206: 2020-21 | E206: 17.26 | F206: 53.62
A207: Karnataka | B207: Maize | C207: Total | D207: 2021-22 | E207: 15.92 | F207: 52.21
A208: Karnataka | B208: Maize | C208: Total | D208: 2022-23 | E208: 19.12 | F208: 59.11
A209: Karnataka | B209: Maize | C209: Total | D209: 2023-24 | E209: 19.72 | F209: 56.29
... A287: Madhya Pradesh | B287: Maize | C287: Rabi | D287: 2021-22 | E287: 0 | F287: 0
A288: Madhya Pradesh | B288: Maize | C288: Rabi | D288: 2022-23
A289: Madhya Pradesh | B289: Maize | C289: Rabi | D289: 2023-24
A290: Madhya Pradesh | B290: Maize | C290: Rabi | D290: 2024-25 | E290: 2.22 | F290: 8.35
A291: Madhya Pradesh | B291: Maize | C291: Rabi | D291: 2025-26 | E291: 1.72 | F291: 9.02
A292: Madhya Pradesh | B292: Maize | C292: Summer | D292: 2016-17
A293: Madhya Pradesh | B293: Maize | C293: Summer | D293: 2017-18
A294: Madhya Pradesh | B294: Maize | C294: Summer | D294: 2018-19
A295: Madhya Pradesh | B295: Maize | C295: Summer | D295: 2019-20
A296: Madhya Pradesh | B296: Maize | C296: Summer | D296: 2020-21
A297: Madhya Pradesh | B297: Maize | C297: Summer | D297: 2021-22
A298: Madhya Pradesh | B298: Maize | C298: Summer | D298: 2022-23
A299: Madhya Pradesh | B299: Maize | C299: Summer | D299: 2023-24 | E299: 0.13 | F299: 0.65
A300: Madhya Pradesh | B300: Maize | C300: Summer | D300: 2024-25 | E300: 0.04 | F300: 0.19
A301: Madhya Pradesh | B301: Maize | C301: Summer | D301: 2025-26 | E301: 0.15 | F301: 0.73
A302: Madhya Pradesh | B302: Maize | C302: Total | D302: 2016-17 | E302: 12.84 | F302: 33.41
A303: Madhya Pradesh | B303: Maize | C303: Total | D303: 2017-18 | E303: 13.53 | F303: 35.37
A304: Madhya Pradesh | B304: Maize | C304: Total | D304: 2018-19 | E304: 12.67 | F304: 41.31
A305: Madhya Pradesh | B305: Maize | C305: Total | D305: 2019-20 | E305: 14.04 | F305: 40.7
A306: Madhya Pradesh | B306: Maize | C306: Total | D306: 2020-21 | E306: 14.05 | F306: 38.82
A307: Madhya Pradesh | B307: Maize | C307: Total | D307: 2021-22 | E307: 14 | F307: 46.07
A308: Madhya Pradesh | B308: Maize | C308: Total | D308: 2022-23 | E308: 14.48 | F308: 46.21
A309: Madhya Pradesh | B309: Maize | C309: Total | D309: 2023-24 | E309: 15.43 | F309: 43.39
A310: Madhya Pradesh | B310: Maize | C310: Total | D310: 2024-25 | E310: 23.03 | F310: 66.42
... A381: Maharashtra | B381: Maize | C381: Rabi | D381: 2025-26 | E381: 6.68 | F381: 19.96
A382: Maharashtra | B382: Maize | C382: Summer | D382: 2016-17
A383: Maharashtra | B383: Maize | C383: Summer | D383: 2017-18
A384: Maharashtra | B384: Maize | C384: Summer | D384: 2018-19
A385: Maharashtra | B385: Maize | C385: Summer | D385: 2019-20
A386: Maharashtra | B386: Maize | C386: Summer | D386: 2020-21
A387: Maharashtra | B387: Maize | C387: Summer | D387: 2021-22
A388: Maharashtra | B388: Maize | C388: Summer | D388: 2022-23 | E388: 0.41 | F388: 0.76
A389: Maharashtra | B389: Maize | C389: Summer | D389: 2023-24 | E389: 0.6 | F389: 1.04
A390: Maharashtra | B390: Maize | C390: Summer | D390: 2024-25 | E390: 0.87 | F390: 2.05
A391: Maharashtra | B391: Maize | C391: Summer | D391: 2025-26 | E391: 0.98 | F391: 1.77
A392: Maharashtra | B392: Maize | C392: Total | D392: 2016-17 | E392: 11.48 | F392: 34.53
A393: Maharashtra | B393: Maize | C393: Total | D393: 2017-18 | E393: 10.64 | F393: 30.51
A394: Maharashtra | B394: Maize | C394: Total | D394: 2018-19 | E394: 9.27 | F394: 17.66
A395: Maharashtra | B395: Maize | C395: Total | D395: 2019-20 | E395: 11.27 | F395: 19.6
A396: Maharashtra | B396: Maize | C396: Total | D396: 2020-21 | E396: 11.82 | F396: 35.2
A397: Maharashtra | B397: Maize | C397: Total | D397: 2021-22 | E397: 12.51 | F397: 35.85
A398: Maharashtra | B398: Maize | C398: Total | D398: 2022-23 | E398: 13.45 | F398: 39.19
A399: Maharashtra | B399: Maize | C399: Total | D399: 2023-24 | E399: 13.26 | F399: 24.5
... A611: Tamil Nadu | B611: Maize | C611: Rabi | D611: 2025-26 | E611: 2.6 | F611: 14.46
A612: Tamil Nadu | B612: Maize | C612: Summer | D612: 2016-17
A613: Tamil Nadu | B613: Maize | C613: Summer | D613: 2017-18
A614: Tamil Nadu | B614: Maize | C614: Summer | D614: 2018-19
A615: Tamil Nadu | B615: Maize | C615: Summer | D615: 2019-20
A616: Tamil Nadu | B616: Maize | C616: Summer | D616: 2020-21
...

Sheet Groundwater
A1: Stage of groundwater extraction by state
A2: Stage (%) = annual extraction / annual extractable resource. Safe <=70, semi-critical 70-90, critical 90-100, over-exploited >100.
A4: Stage of extraction (%), as printed | B4: 2017 | C4: 2020 | D4: 2022 | E4: 2023 | F4: 2024 | G4: Change 2017-2024 (pp)
A5: Bihar | B5: 45.76 | C5: 51.14 | D5: 44.94 | E5: 44.76 | F5: 45.54 | G5: =F5-B5 -> -0.22
A6: Haryana | B6: 136.91 | C6: 134.56 | D6: 134.14 | E6: 135.74 | F6: 135.96 | G6: =F6-B6 -> -0.95
A7: Karnataka | B7: 69.87 | C7: 64.85 | D7: 69.93 | E7: 66.26 | F7: 68.44 | G7: =F7-B7 -> -1.43
A8: Madhya Pradesh | B8: 54.76 | C8: 56.82 | D8: 59.1 | E8: 58.75 | F8: 58.4 | G8: =F8-B8 -> 3.64
A9: Maharashtra | B9: 54.62 | C9: 54.99 | D9: 54.68 | E9: 53.83 | F9: 52.99 | G9: =F9-B9 -> -1.63
A10: Punjab | B10: 165.77 | C10: 164.42 | D10: 165.99 | E10: 163.76 | F10: 156.87 | G10: =F10-B10 -> -8.9
A11: Rajasthan | B11: 139.88 | C11: 150.22 | D11: 151.07 | E11: 148.77 | F11: 149.86 | G11: =F11-B11 -> 9.98
A12: Tamil Nadu | B12: 80.94 | C12: 82.93 | D12: 75.59 | E12: 73.91 | F12: 74.26 | G12: =F12-B12 -> -6.68
A13: Telangana | B13: 65.45 | C13: 53.32 | D13: 41.6 | E13: 38.65 | F13: 45.91 | G13: =F13-B13 -> -19.54
A14: Uttar Pradesh | B14: 70.18 | C14: 68.83 | D14: 70.66 | E14: 70.76 | F14: 70.45 | G14: =F14-B14 -> 0.27
A15: All India | B15: 63.33 | C15: 61.6 | D15: 60.08 | E15: 59.26 | F15: 60.475 | G15: =F15-B15 -> -2.855
A17: Annual extraction (bcm) | B17: 2017 | C17: 2020 | D17: 2022 | E17: 2023 | F17: 2024
A18: Bihar | B18: 13.26 | C18: 13.02 | D18: 13.5 | E18: 13.75 | F18: 14.1
A19: Haryana | B19: 12.5 | C19: 11.61 | D19: 11.54 | E19: 11.8 | F19: 12.72
A20: Karnataka | B20: 10.34 | C20: 10.63 | D20: 11.22 | E20: 11.32 | F20: 11.55
A21: Madhya Pradesh | B21: 18.88 | C21: 18.97 | D21: 19.25 | E21: 19.3 | F21: 19.85
A22: Maharashtra | B22: 16.33 | C22: 16.63 | D22: 16.65 | E22: 16.66 | F22: 16.5
A23: Punjab | B23: 35.78 | C23: 33.85 | D23: 28.02 | E23: 27.8 | F23: 27.66
A24: Rajasthan | B24: 16.77 | C24: 16.63 | D24: 16.56 | E24: 16.74 | F24: 17.05
A25: Tamil Nadu | B25: 14.73 | C25: 14.67 | D25: 14.43 | E25: 14.42 | F25: 14.45
A26: Telangana | B26: 8.09 | C26: 8.01 | D26: 8 | E26: 8.09 | F26: 8.47
A27: Uttar Pradesh | B27: 45.84 | C27: 46.03 | D27: 46.14 | E27: 46.4 | F27: 46.76
A28: All India | B28: 248.69 | C28: 244.92 | D28: 239.16 | E28: 241.34 | F28: 245.646
A30: Annual extractable resource (bcm) | B30: 2017 | C30: 2020 | D30: 2022 | E30: 2023 | F30: 2024
A31: Bihar | B31: 28.99 | C31: 25.46 | D31: 30.04 | E31: 30.72 | F31: 30.95
A32: Haryana | B32: 9.13 | C32: 8.63 | D32: 8.61 | E32: 8.69 | F32: 9.36
A33: Karnataka | B33: 14.79 | C33: 16.4 | D33: 16.04 | E33: 17.08 | F33: 16.88
A34: Madhya Pradesh | B34: 34.47 | C34: 33.38 | D34: 32.58 | E34: 32.85 | F34: 33.99
A35: Maharashtra | B35: 29.9 | C35: 30.25 | D35: 30.45 | E35: 30.95 | F35: 31.15
A36: Punjab | B36: 21.58 | C36: 20.59 | D36: 17.07 | E36: 16.98 | F36: 17.63
A37: Rajasthan | B37: 11.99 | C37: 11.07 | D37: 10.96 | E37: 11.25 | F37: 11.37
A38: Tamil Nadu | B38: 18.2 | C38: 17.69 | D38: 19.09 | E38: 19.51 | F38: 19.46
A39: Telangana | B39: 12.37 | C39: 15.03 | D39: 19.25 | E39: 20.92 | F39: 18.44
A40: Uttar Pradesh | B40: 65.32 | C40: 66.88 | D40: 65.3 | E40: 65.57 | F40: 66.38
A41: All India | B41: 392.7 | C41: 397.62 | D41: 398.08 | E41: 407.21 | F41: 406.194
A43: Cross-check: computed stage (%) | B43: 2017 | C43: 2020 | D43: 2022 | E43: 2023 | F43: 2024 | G43: Max gap vs printed (pp)
A44: Bihar | B44: =B18/B31*100 -> 45.73991 | C44: =C18/C31*100 -> 51.139042 | D44: =D18/D31*100 -> 44.94008 | E44: =E18/E31*100 -> 44.759115 | F44: =F18/F31*100 -> 45.557351 | G44: =MAX(ABS(B44-B5),ABS(C44-C5),ABS(D44-D5),ABS(E44-E5),ABS(F44-F5)) -> 0.020089686
A45: Haryana | B45: =B19/B32*100 -> 136.91128 | C45: =C19/C32*100 -> 134.53071 | D45: =D19/D32*100 -> 134.0302 | E45: =E19/E32*100 -> 135.78826 | F45: =F19/F32*100 -> 135.89744 | G45: =MAX(ABS(B45-B6),ABS(C45-C6),ABS(D45-D6),ABS(E45-E6),ABS(F45-F6)) -> 0.10980256
A46: Karnataka | B46: =B20/B33*100 -> 69.912103 | C46: =C20/C33*100 -> 64.817073 | D46: =D20/D33*100 -> 69.950125 | E46: =E20/E33*100 -> 66.276347 | F46: =F20/F33*100 -> 68.424171 | G46: =MAX(ABS(B46-B7),ABS(C46-C7),ABS(D46-D7),ABS(E46-E7),ABS(F46-F7)) -> 0.042102772
A47: Madhya Pradesh | B47: =B21/B34*100 -> 54.772266 | C47: =C21/C34*100 -> 56.830437 | D47: =D21/D34*100 -> 59.085328 | E47: =E21/E34*100 -> 58.751903 | F47: =F21/F34*100 -> 58.399529 | G47: =MAX(ABS(B47-B8),ABS(C47-C8),ABS(D47-D8),ABS(E47-E8),ABS(F47-F8)) -> 0.014671578
A48: Maharashtra | B48: =B22/B35*100 -> 54.615385 | C48: =C22/C35*100 -> 54.975207 | D48: =D22/D35*100 -> 54.679803 | E48: =E22/E35*100 -> 53.828756 | F48: =F22/F35*100 -> 52.969502 | G48: =MAX(ABS(B48-B9),ABS(C48-C9),ABS(D48-D9),ABS(E48-E9),ABS(F48-F9)) -> 0.020497592
A49: Punjab | B49: =B23/B36*100 -> 165.80167 | C49: =C23/C36*100 -> 164.40019 | D49: =D23/D36*100 -> 164.14763 | E49: =E23/E36*100 -> 163.72203 | F49: =F23/F36*100 -> 156.89166 | G49: =MAX(ABS(B49-B10),ABS(C49-C10),ABS(D49-D10),ABS(E49-E10),ABS(F49-F10)) -> 1.8423726
A50: Rajasthan | B50: =B24/B37*100 -> 139.86656 | C50: =C24/C37*100 -> 150.22584 | D50: =D24/D37*100 -> 151.09489 | E50: =E24/E37*100 -> 148.8 | F50: =F24/F37*100 -> 149.95602 | G50: =MAX(ABS(B50-B11),ABS(C50-C11),ABS(D50-D11),ABS(E50-E11),ABS(F50-F11)) -> 0.096024626
A51: Tamil Nadu | B51: =B25/B38*100 -> 80.934066 | C51: =C25/C38*100 -> 82.928208 | D51: =D25/D38*100 -> 75.589314 | E51: =E25/E38*100 -> 73.910815 | F51: =F25/F38*100 -> 74.254882 | G51: =MAX(ABS(B51-B12),ABS(C51-C12),ABS(D51-D12),ABS(E51-E12),ABS(F51-F12)) -> 0.0059340659
A52: Telangana | B52: =B26/B39*100 -> 65.400162 | C52: =C26/C39*100 -> 53.293413 | D52: =D26/D39*100 -> 41.558442 | E52: =E26/E39*100 -> 38.671128 | F52: =F26/F39*100 -> 45.932755 | G52: =MAX(ABS(B52-B13),ABS(C52-C13),ABS(D52-D13),ABS(E52-E13),ABS(F52-F13)) -> 0.049838319
A53: Uttar Pradesh | B53: =B27/B40*100 -> 70.177587 | C53: =C27/C40*100 -> 68.824761 | D53: =D27/D40*100 -> 70.658499 | E53: =E27/E40*100 -> 70.764069 | F53: =F27/F40*100 -> 70.442904 | G53: =MAX(ABS(B53-B14),ABS(C53-C14),ABS(D53-D14),ABS(E53-E14),ABS(F53-F14)) -> 0.0070955107
A54: All India | B54: =B28/B41*100 -> 63.32824 | C54: =C28/C41*100 -> 61.596499 | D54: =D28/D41*100 -> 60.078376 | E54: =E28/E41*100 -> 59.266717 | F54: =F28/F41*100 -> 60.475044 | G54: =MAX(ABS(B54-B15),ABS(C54-C15),ABS(D54-D15),ABS(E54-E15),ABS(F54-F15)) -> 0.0067174185
A56: Source: RBI Handbook of Statistics on Indian States 2024-25, Table 107 (11 Dec 2025), compiling CGWB National Compilations on Dynamic Ground Water Resources.
A57: Conflict: Punjab 2022 printed as 165.99% by RBI; CGWB's Punjab 2024 report gives 164.11% for 2022, which matches 28.02/17.07. Use 164.11 in analysis.
A58: Check: 2017 and 2020 extraction totals match Lok Sabha AU3018 (sansad) exactly.
A59: Gap: 2025 state values (national 60.63%) and the irrigation / industrial / domestic split are not yet collected. See Gaps tab.

Sheet Rainfall
A1: Southwest monsoon rainfall (June-September) by state
A2: Actual and normal in mm; departure (%) = actual/normal - 1. Normals change slightly between IMD reports.
A4: Departure from normal (%), as printed | B4: 2015 | C4: 2016 | D4: 2017 | E4: 2018 | F4: 2019 | G4: 2020 | H4: 2021 | I4: 2022 | J4: 2023 | K4: 2024
A5: Bihar | B5: -0.27 | C5: -0.03 | E5: -0.25 | F5: 0.03 | G5: 0.25 | H5: 0.03 | I5: -0.31
A6: Haryana | B6: -0.37 | C6: -0.28 | E6: -0.05 | F6: -0.42 | G6: -0.14 | H6: 0.3 | I6: 0.09
A7: Karnataka | B7: -0.2 | C7: -0.15 | E7: -0.06 | F7: 0.23 | G7: 0.27 | H7: 0.03 | I7: 0.29
A8: Madhya Pradesh | B8: -0.11 | C8: 0.19 | E8: -0.08 | F8: 0.44 | G8: 0.05 | H8: 0 | I8: 0.23
A9: Maharashtra | B9: -0.27 | C9: 0.16 | E9: -0.08 | F9: 0.32 | G9: 0.16 | H9: 0.19 | I9: 0.23
A10: Punjab | B10: -0.31 | C10: -0.28 | E10: 0.16 | F10: -0.07 | G10: -0.17 | H10: -0.07 | I10: -0.06
A11: Rajasthan | B11: 0.1 | C11: 0.28 | E11: -0.06 | F11: 0.41 | G11: 0.08 | H11: 0.17 | I11: 0.37
A12: Tamil Nadu | B12: -0.1 | C12: -0.19 | E12: -0.08 | F12: 0.17 | G12: 0.27 | H12: 0.17 | I12: 0.45
A13: Telangana | B13: -0.2 | C13: 0.19 | E13: -0.03 | F13: 0.06 | G13: 0.46 | H13: 0.39 | I13: 0.46
A14: Uttar Pradesh | B14: -0.46 | C14: -0.14 | E14: -0.1 | F14: -0.09 | G14: -0.18 | H14: -0.05 | I14: -0.29
A16: Actual rainfall (mm) | B16: 2015 | C16: 2016 | D16: 2017 | E16: 2018 | F16: 2019 | G16: 2020 | H16: 2021 | I16: 2022 | J16: 2023 | K16: 2024
A17: Bihar | B17: 745 | C17: 994.1 | E17: 770.8 | F17: 1049.4 | G17: 1272.4 | H17: 1044.3 | I17: 683.7
A18: Haryana | B18: 287.9 | C18: 332.1 | E18: 436.1 | F18: 255.2 | G18: 376.1 | H18: 571.3 | I18: 464.7
A19: Karnataka | B19: 664.7 | C19: 710.8 | E19: 780.3 | F19: 1032.1 | G19: 1063.9 | H19: 865.4 | I19: 1075.2
A20: Madhya Pradesh | B20: 843.8 | C20: 1131 | E20: 873.1 | F20: 1351.1 | G20: 991.7 | H20: 942.7 | I20: 1169.5
A21: Maharashtra | B21: 733 | C21: 1164.9 | E21: 923.9 | F21: 1329.8 | G21: 1166.1 | H21: 1194.3 | I21: 1219.8
A22: Punjab | B22: 338 | C22: 352 | E22: 569.1 | F22: 434.5 | G22: 387.5 | H22: 436.8 | I22: 414
A23: Rajasthan | B23: 460.3 | C23: 535.8 | E23: 393.7 | F23: 583.7 | G23: 450.2 | H23: 485.3 | I23: 596
A24: Tamil Nadu | B24: 286 | C24: 257.8 | E24: 290.7 | F24: 401.6 | G24: 425.8 | H24: 393.4 | I24: 476.8
A25: Telangana | B25: 600.8 | C25: 899.8 | E25: 732.9 | F25: 806.9 | G25: 1095.8 | H25: 1044.2 | I25: 1072.7
A26: Uttar Pradesh | B26: 459.3 | C26: 731.5 | E26: 765.4 | F26: 719.9 | G26: 649.7 | H26: 749.2 | I26: 533.4
A28: Normal rainfall (mm) | B28: 2015 | C28: 2016 | D28: 2017 | E28: 2018 | F28: 2019 | G28: 2020 | H28: 2021 | I28: 2022 | J28: 2023 | K28: 2024
A29: Bihar | B29: 1027.6 | C29: 1027.6 | E29: 1027.6 | F29: 1017.2 | G29: 1017.2 | H29: 1017.2 | I29: 992.2
A30: Haryana | B30: 459.8 | C30: 459.8 | E30: 459.8 | F30: 438.6 | G30: 438.6 | H30: 438.6 | I30: 426
A31: Karnataka | B31: 832.2 | C31: 832.2 | E31: 832.2 | F31: 840.7 | G31: 840.7 | H31: 840.7 | I31: 831.8
A32: Madhya Pradesh | B32: 952.3 | C32: 952.3 | E32: 952.3 | F32: 940.6 | G32: 940.6 | H32: 940.6 | I32: 949.5
A33: Maharashtra | B33: 1007.3 | C33: 1007.3 | E33: 1007.3 | F33: 1004.2 | G33: 1004.2 | H33: 1004.2 | I33: 994.5
A34: Punjab | B34: 491.9 | C34: 491.9 | E34: 491.9 | F34: 467.3 | G34: 467.3 | H34: 467.3 | I34: 439.8
A35: Rajasthan | B35: 419 | C35: 419 | E35: 419 | F35: 415 | G35: 415 | H35: 415 | I35: 435.6
A36: Tamil Nadu | B36: 317 | C36: 317 | E36: 317 | F36: 341.9 | G36: 336 | H36: 336 | I36: 328.4
A37: Telangana | B37: 755.2 | C37: 755.2 | E37: 759.2 | F37: 759.6 | G37: 751.9 | H37: 751.9 | I37: 734.8
A38: Uttar Pradesh | B38: 846.1 | C38: 846.1 | E38: 846.1 | F38: 790.2 | G38: 790.2 | H38: 790.2 | I38: 746.2
A40: Cross-check: computed departure | B40: 2015 | C40: 2016 | D40: 2017 | E40: 2018 | F40: 2019 | G40: 2020 | H40: 2021 | I40: 2022 | J40: 2023 | K40: 2024
A41: Bihar | B41: =IF(B29="","",B17/B29-1) -> -0.27500973 | C41: =IF(C29="","",C17/C29-1) -> -0.032600234 | D41: =IF(D29="","",D17/D29-1) | E41: =IF(E29="","",E17/E29-1) -> -0.24990269 | F41: =IF(F29="","",F17/F29-1) -> 0.031655525 | G41: =IF(G29="","",G17/G29-1) -> 0.25088478 | H41: =IF(H29="","",H17/H29-1) -> 0.026641762 | I41: =IF(I29="","",I17/I29-1) -> -0.31092522 | ... K41: =IF(K29="","",K17/K29-1)
A42: Haryana | B42: =IF(B30="","",B18/B30-1) -> -0.3738582 | C42: =IF(C30="","",C18/C30-1) -> -0.27772945 | D42: =IF(D30="","",D18/D30-1) | E42: =IF(E30="","",E18/E30-1) -> -0.05154415 | F42: =IF(F30="","",F18/F30-1) -> -0.41814865 | G42: =IF(G30="","",G18/G30-1) -> -0.14249886 | H42: =IF(H30="","",H18/H30-1) -> 0.30255358 | I42: =IF(I30="","",I18/I30-1) -> 0.09084507 | ... K42: =IF(K30="","",K18/K30-1)
A43: Karnataka | B43: =IF(B31="","",B19/B31-1) -> -0.20127373 | C43: =IF(C31="","",C19/C31-1) -> -0.14587839 | D43: =IF(D31="","",D19/D31-1) | E43: =IF(E31="","",E19/E31-1) -> -0.062364816 | F43: =IF(F31="","",F19/F31-1) -> 0.22766742 | G43: =IF(G31="","",G19/G31-1) -> 0.26549304 | H43: =IF(H31="","",H19/H31-1) -> 0.029380278 | I43: =IF(I31="","",I19/I31-1) -> 0.29261842 | ... K43: =IF(K31="","",K19/K31-1)
A44: Madhya Pradesh | B44: =IF(B32="","",B20/B32-1) -> -0.11393468 | C44: =IF(C32="","",C20/C32-1) -> 0.18765095 | D44: =IF(D32="","",D20/D32-1) | E44: =IF(E32="","",E20/E32-1) -> -0.083167069 | F44: =IF(F32="","",F20/F32-1) -> 0.43642356 | G44: =IF(G32="","",G20/G32-1) -> 0.054327025 | H44: =IF(H32="","",H20/H32-1) -> 0.0022326175 | I44: =IF(I32="","",I20/I32-1) -> 0.2317009 | ... K44: =IF(K32="","",K20/K32-1)
A45: Maharashtra | B45: =IF(B33="","",B21/B33-1) -> -0.27231212 | C45: =IF(C33="","",C21/C33-1) -> 0.15645786 | D45: =IF(D33="","",D21/D33-1) | E45: =IF(E33="","",E21/E33-1) -> -0.082795592 | F45: =IF(F33="","",F21/F33-1) -> 0.3242382 | G45: =IF(G33="","",G21/G33-1) -> 0.16122286 | H45: =IF(H33="","",H21/H33-1) -> 0.18930492 | I45: =IF(I33="","",I21/I33-1) -> 0.226546 | ... K45: =IF(K33="","",K21/K33-1)
A46: Punjab | B46: =IF(B34="","",B22/B34-1) -> -0.31286847 | C46: =IF(C34="","",C22/C34-1) -> -0.2844074 | D46: =IF(D34="","",D22/D34-1) | E46: =IF(E34="","",E22/E34-1) -> 0.15694247 | F46: =IF(F34="","",F22/F34-1) -> -0.070190456 | G46: =IF(G34="","",G22/G34-1) -> -0.17076824 | H46: =IF(H34="","",H22/H34-1) -> -0.065268564 | I46: =IF(I34="","",I22/I34-1) -> -0.058663029 | ... K46: =IF(K34="","",K22/K34-1)
A47: Rajasthan | B47: =IF(B35="","",B23/B35-1) -> 0.098568019 | C47: =IF(C35="","",C23/C35-1) -> 0.27875895 | D47: =IF(D35="","",D23/D35-1) | E47: =IF(E35="","",E23/E35-1) -> -0.060381862 | F47: =IF(F35="","",F23/F35-1) -> 0.40650602 | G47: =IF(G35="","",G23/G35-1) -> 0.084819277 | H47: =IF(H35="","",H23/H35-1) -> 0.16939759 | I47: =IF(I35="","",I23/I35-1) -> 0.36822773 | ... K47: =IF(K35="","",K23/K35-1)
A48: Tamil Nadu | B48: =IF(B36="","",B24/B36-1) -> -0.097791798 | C48: =IF(C36="","",C24/C36-1) -> -0.18675079 | D48: =IF(D36="","",D24/D36-1) | E48: =IF(E36="","",E24/E36-1) -> -0.0829653 | F48: =IF(F36="","",F24/F36-1) -> 0.17461246 | G48: =IF(G36="","",G24/G36-1) -> 0.2672619 | H48: =IF(H36="","",H24/H36-1) -> 0.17083333 | I48: =IF(I36="","",I24/I36-1) -> 0.45188794 | ... K48: =IF(K36="","",K24/K36-1)
A49: Telangana | B49: =IF(B37="","",B25/B37-1) -> -0.20444915 | C49: =IF(C37="","",C25/C37-1) -> 0.19147246 | D49: =IF(D37="","",D25/D37-1) | E49: =IF(E37="","",E25/E37-1) -> -0.034641728 | F49: =IF(F37="","",F25/F37-1) -> 0.062269616 | G49: =IF(G37="","",G25/G37-1) -> 0.45737465 | H49: =IF(H37="","",H25/H37-1) -> 0.3887485 | I49: =IF(I37="","",I25/I37-1) -> 0.45985302 | ... K49: =IF(K37="","",K25/K37-1)
A50: Uttar Pradesh | B50: =IF(B38="","",B26/B38-1) -> -0.45715636 | C50: =IF(C38="","",C26/C38-1) -> -0.13544498 | D50: =IF(D38="","",D26/D38-1) | E50: =IF(E38="","",E26/E38-1) -> -0.095378797 | F50: =IF(F38="","",F26/F38-1) -> -0.088964819 | G50: =IF(G38="","",G26/G38-1) -> -0.17780309 | H50: =IF(H38="","",H26/H38-1) -> -0.051885599 | I50: =IF(I38="","",I26/I38-1) -> -0.28517824 | ... K50: =IF(K38="","",K26/K38-1)
A52: Sources: MoES / IMD Parliament answers: Lok Sabha US 4446 (14 Dec 2016) for 2015-16; Rajya Sabha 165 (3 Aug 2021) for 2018-19; Rajya Sabha 25 (27 Jul 2023) for 2020-22.
A53: The 2020 rows in RS 165 are misaligned in the source; 2020 is taken from the 2023 answer instead.
A54: Gap (yellow): 2017, 2023, 2024 not yet found in an official state-level table.

Sheet Sugarcane
A1: Sugarcane area and production by state
A4: Area ('000 ha), RBI T80 | B4: 2014-15 | C4: 2015-16 | D4: 2016-17 | E4: 2017-18 | F4: 2018-19 | G4: 2019-20 | H4: 2020-21 | I4: 2021-22 | J4: 2022-23 | K4: Change 2015-16 to 2022-23
A5: Bihar | B5: 254.3 | C5: 244 | D5: 239.6 | E5: 233.8 | F5: 225.6 | G5: 223.9 | H5: 221.1 | I5: 211.2 | J5: 209.9 | K5: =IFERROR(J5/C5-1,"") -> -0.1397541
A6: Haryana | B6: 97 | C6: 93 | D6: 102 | E6: 114 | F6: 108.7 | G6: 96.3 | H6: 99 | I6: 107.7 | J6: 107.8 | K6: =IFERROR(J6/C6-1,"") -> 0.15913978
A7: Karnataka | B7: 480 | C7: 450 | D7: 397 | E7: 370.3 | F7: 471.2 | G7: 429 | H7: 443 | I7: 637 | J7: 694 | K7: =IFERROR(J7/C7-1,"") -> 0.54222222
A8: Madhya Pradesh | B8: 111 | C8: 103 | D8: 92 | E8: 98 | F8: 108 | G8: 125 | H8: 95 | I8: 93 | J8: 92 | K8: =IFERROR(J8/C8-1,"") -> -0.10679612
A9: Maharashtra | B9: 1030 | C9: 987 | D9: 633.3 | E9: 902 | F9: 1162.8 | G9: 822.4 | H9: 1142.8 | I9: 1261.7 | J9: 1359.3 | K9: =IFERROR(J9/C9-1,"") -> 0.37720365
A10: Punjab | B10: 94 | C10: 90 | D10: 88 | E10: 96 | F10: 95 | G10: 91 | H10: 89.3 | I10: 86.8 | J10: 90.2 | K10: =IFERROR(J10/C10-1,"") -> 0.0022222222
A11: Rajasthan | B11: 5.6 | C11: 6.1 | D11: 6.9 | E11: 5.4 | F11: 5.4 | G11: 4.5 | H11: 5 | I11: 4.2 | J11: 3.5 | K11: =IFERROR(J11/C11-1,"") -> -0.42622951
A12: Tamil Nadu | B12: 263.1 | C12: 252.3 | D12: 218.3 | E12: 171.9 | F12: 166.4 | G12: 131.2 | H12: 127.7 | I12: 148 | J12: 161.4 | K12: =IFERROR(J12/C12-1,"") -> -0.36028537
A13: Telangana | B13: 38 | C13: 35 | D13: 29 | E13: 35 | F13: 40 | G13: 26 | H13: 22 | I13: 28 | J13: 33 | K13: =IFERROR(J13/C13-1,"") -> -0.057142857
A14: Uttar Pradesh | B14: 2140.8 | C14: 2169 | D14: 2160 | E14: 2234 | F14: 2224 | G14: 2208 | H14: 2180 | I14: 2177 | J14: 2736.1 | K14: =IFERROR(J14/C14-1,"") -> 0.26145689
A15: All India | B15: 5066.8 | C15: 4927.1 | D15: 4435.7 | E15: 4737.1 | F15: 5061.1 | G15: 4602.7 | H15: 4851.2 | I15: 5175.4 | J15: 5883.5 | K15: =IFERROR(J15/C15-1,"") -> 0.19411013
A16: Source: RBI Handbook 2023, Table 80 (Ministry of Agriculture). 2022-23 = 3rd advance estimate (later revised, e.g. UP 2,795 in ICAR table).
A18: Area (lakh ha), ICAR-SBI | B18: 2018-19 | C18: 2019-20 | D18: 2020-21 | E18: 2021-22 | F18: 2022-23 | G18: 2023-24
A19: Bihar | B19: 2.26 | C19: 2.24 | D19: 2.19 | E19: 2.11 | F19: 2.1 | G19: 2.02
A20: Haryana | B20: 1.09 | C20: 0.96 | D20: 0.99 | E20: 1.08 | F20: 1.08 | G20: 0.9
A21: Karnataka | B21: 4.71 | C21: 4.29 | D21: 4.43 | E21: 6.37 | F21: 6.59 | G21: 6.26
A22: Madhya Pradesh | B22: 1.08 | C22: 1.25 | D22: 1.1 | E22: 0.93 | F22: 0.92 | G22: 1.02
A23: Maharashtra | B23: 11.63 | C23: 8.22 | D23: 11.43 | E23: 12.62 | F23: 13.59 | G23: 14
A24: Punjab | B24: 0.95 | C24: 0.91 | D24: 0.89 | E24: 0.87 | F24: 0.9 | G24: 0.96
A25: Tamil Nadu | B25: 1.66 | C25: 1.31 | D25: 1.25 | E25: 1.48 | F25: 1.59 | G25: 1.35
A26: Telangana | B26: 0.4 | C26: 0.26 | D26: 0.2 | E26: 0.28 | F26: 0.28 | G26: 0.27
A27: Uttar Pradesh | B27: 22.24 | C27: 22.08 | D27: 21.8 | E27: 21.77 | F27: 27.95 | G27: 25.28
A28: All India | B28: 50.61 | C28: 46.03 | D28: 48.57 | E28: 51.75 | F28: 58.85 | G28: 56.48
A30: Production (million t), ICAR-SBI | B30: 2018-19 | C30: 2019-20 | D30: 2020-21 | E30: 2021-22 | F30: 2022-23 | G30: 2023-24 | H30: Change 2018-19 to 2023-24
A31: Bihar | B31: 20.12 | C31: 13.58 | D31: 10.71 | E31: 12.03 | F31: 12.74 | G31: 11.39 | H31: =G31/B31-1 -> -0.43389662
A32: Haryana | B32: 8.51 | C32: 7.73 | D32: 8.53 | E32: 8.82 | F32: 8.86 | G32: 7.46 | H32: =G32/B32-1 -> -0.12338425
A33: Karnataka | B33: 42.41 | C33: 38.18 | D33: 42.09 | E33: 61.15 | F33: 59.35 | G33: 53.2 | H33: =G33/B33-1 -> 0.25442113
A34: Madhya Pradesh | B34: 5.28 | C34: 7.43 | D34: 5.88 | E34: 5.38 | F34: 6.44 | G34: 7.14 | H34: =G34/B34-1 -> 0.35227273
A35: Maharashtra | B35: 89.77 | C35: 69.31 | D35: 101.6 | E35: 116.08 | F35: 123.97 | G35: 105.99 | H35: =G35/B35-1 -> 0.18068397
A36: Punjab | B36: 7.77 | C36: 7.3 | D36: 7.49 | E36: 7.13 | F36: 7.51 | G36: 7.99 | H36: =G36/B36-1 -> 0.028314028
A37: Tamil Nadu | B37: 17.14 | C37: 14.12 | D37: 12.8 | E37: 16.17 | F37: 17.66 | G37: 14.41 | H37: =G37/B37-1 -> -0.15927655
A38: Telangana | B38: 3.18 | C38: 2.01 | D38: 1.36 | E38: 2.87 | F38: 2.94 | G38: 2.32 | H38: =G38/B38-1 -> -0.27044025
A39: Uttar Pradesh | B39: 179.71 | C39: 179.54 | D39: 177.67 | E39: 179.17 | F39: 224.25 | G39: 205.63 | H39: =G39/B39-1 -> 0.14423237
A40: All India | B40: 405.42 | C40: 370.5 | D40: 399.26 | E40: 439.43 | F40: 490.53 | G40: 446.43 | H40: =G40/B40-1 -> 0.10115436
A41: Source: ICAR-Sugarcane Breeding Institute, StatisticsAPY-23-24 (citing DES / E&S DAC); 2023-24 = 2nd advance estimate. Rajasthan not listed.
A43: Yield (kg/ha), Lok Sabha AU1760 | B43: 2015-16 | C43: 2016-17 | D43: 2017-18
A44: Bihar | B44: 51837 | C44: 54415 | D44: 59138
A45: Haryana | B45: 71957 | C45: 80618 | D45: 84499
A46: Karnataka | B46: 84075 | C46: 68962 | D46: 84081
A47: Madhya Pradesh | B47: 51272 | C47: 51413 | D47: 55408
A48: Maharashtra | B48: 74650 | C48: 82524 | D48: 92000
A49: Punjab | B49: 73411 | C49: 81273 | D49: 83580
A50: Rajasthan | B50: 86511 | C50: 71294 | D50: 70364
A51: Tamil Nadu | B51: 101059 | C51: 86995 | D51: 99814
A52: Telangana | B52: 68714 | C52: 71069 | D52: 74413
A53: Uttar Pradesh | B53: 67029 | C53: 64893 | D53: 79245
A54: All India | B54: 70720 | C54: 69001 | D54: 80198
A56: Production (million t) = area x yield | B56: 2015-16 | C56: 2016-17 | D56: 2017-18
A57: Bihar | B57: =C5*B44/1000000 -> 12.648228 | C57: =D5*C44/1000000 -> 13.037834 | D57: =E5*D44/1000000 -> 13.826464
A58: Haryana | B58: =C6*B45/1000000 -> 6.692001 | C58: =D6*C45/1000000 -> 8.223036 | D58: =E6*D45/1000000 -> 9.632886
A59: Karnataka | B59: =C7*B46/1000000 -> 37.83375 | C59: =D7*C46/1000000 -> 27.377914 | D59: =E7*D46/1000000 -> 31.135194
A60: Madhya Pradesh | B60: =C8*B47/1000000 -> 5.281016 | C60: =D8*C47/1000000 -> 4.729996 | D60: =E8*D47/1000000 -> 5.429984
A61: Maharashtra | B61: =C9*B48/1000000 -> 73.67955 | C61: =D9*C48/1000000 -> 52.262449 | D61: =E9*D48/1000000 -> 82.984
A62: Punjab | B62: =C10*B49/1000000 -> 6.60699 | C62: =D10*C49/1000000 -> 7.152024 | D62: =E10*D49/1000000 -> 8.02368
A63: Rajasthan | B63: =C11*B50/1000000 -> 0.5277171 | C63: =D11*C50/1000000 -> 0.4919286 | D63: =E11*D50/1000000 -> 0.3799656
A64: Tamil Nadu | B64: =C12*B51/1000000 -> 25.497186 | C64: =D12*C51/1000000 -> 18.991008 | D64: =E12*D51/1000000 -> 17.158027
A65: Telangana | B65: =C13*B52/1000000 -> 2.40499 | C65: =D13*C52/1000000 -> 2.061001 | D65: =E13*D52/1000000 -> 2.604455
A66: Uttar Pradesh | B66: =C14*B53/1000000 -> 145.3859 | C66: =D14*C53/1000000 -> 140.16888 | D66: =E14*D53/1000000 -> 177.03333
A67: All India | B67: =C15*B54/1000000 -> 348.44451 | C67: =D15*C54/1000000 -> 306.06774 | D67: =E15*D54/1000000 -> 379.90595
A68: Yield source: Lok Sabha AU1760 (2 Jul 2019), Ministry of Agriculture. Production computed here; area from RBI T80.

Sheet Rice
A1: Rice area and production by state
A4: Area ('000 ha), RBI T69 | B4: 2014-15 | C4: 2015-16 | D4: 2016-17 | E4: 2017-18 | F4: 2018-19 | G4: 2019-20 | H4: 2020-21 | I4: 2021-22 | J4: 2022-23 | K4: Change 2015-16 to 2022-23
A5: Bihar | B5: 3263.4 | C5: 3232.3 | D5: 3339.8 | E5: 3307 | F5: 3159.7 | G5: 2886.4 | H5: 3020.9 | I5: 3091.4 | J5: 2940.6 | K5: =J5/C5-1 -> -0.090245336
A6: Haryana | B6: 1287 | C6: 1354 | D6: 1386 | E6: 1422 | F6: 1447 | G6: 1447 | H6: 1327.2 | I6: 1281 | J6: 1519.7 | K6: =J6/C6-1 -> 0.12237814
A7: Karnataka | B7: 1326 | C7: 1110 | D7: 1034 | E7: 993 | F7: 1139.1 | G7: 1185 | H7: 1397.1 | I7: 1397.9 | J7: 1300 | K7: =J7/C7-1 -> 0.17117117
A8: Madhya Pradesh | B8: 2153 | C8: 2024 | D8: 2289 | E8: 2035 | F8: 2391 | G8: 2016 | H8: 2117 | I8: 2109 | J8: 3413.8 | K8: =J8/C8-1 -> 0.68666008
A9: Maharashtra | B9: 1551 | C9: 1503 | D9: 1535.3 | E9: 1451 | F9: 1464.9 | G9: 1553 | H9: 1560.6 | I9: 1651.8 | J9: 1718.1 | K9: =J9/C9-1 -> 0.14311377
A10: Punjab | B10: 2894 | C10: 2975 | D10: 2898 | E10: 3065 | F10: 3103 | G10: 2920 | H10: 2928 | I10: 2969 | J10: 3028.5 | K10: =J10/C10-1 -> 0.017983193
A11: Rajasthan | B11: 167.8 | C11: 182.9 | D11: 197.8 | E11: 190.6 | F11: 197.8 | G11: 219.5 | H11: 231.5 | I11: 196.5 | J11: 234.3 | K11: =J11/C11-1 -> 0.28102788
A12: Tamil Nadu | B12: 1795 | C12: 2000.2 | D12: 1442.8 | E12: 1828.9 | F12: 1721.3 | G12: 1907.4 | H12: 2036.2 | I12: 2217.3 | J12: 2150.7 | K12: =J12/C12-1 -> 0.075242476
A13: Telangana | B13: 1415 | C13: 1046 | D13: 1682.2 | E13: 1962 | F13: 1932 | G13: 2011 | H13: 3186.4 | I13: 3654.9 | J13: 4548.4 | K13: =J13/C13-1 -> 3.3483748
A14: Uttar Pradesh | B14: 5872 | C14: 5862 | D14: 5992 | E14: 5814 | F14: 5748 | G14: 5737 | H14: 5678 | I14: 5703 | J14: 5796 | K14: =J14/C14-1 -> -0.011258956
A15: All India | B15: 44110.6 | C15: 43499.2 | D15: 43993.4 | E15: 43774.1 | F15: 44156.5 | G15: 43662.3 | H15: 45768.7 | I15: 46278.7 | J15: 47666.4 | K15: =J15/C15-1 -> 0.095799463
A16: Source: RBI Handbook 2023, Table 69 (Ministry of Agriculture). 2022-23 = 3rd advance estimate.
A18: Production ('000 t), RBI T60 | B18: 2014-15 | C18: 2015-16 | D18: 2016-17 | E18: 2017-18 | F18: 2018-19 | G18: 2019-20 | H18: 2020-21 | I18: 2021-22 | J18: 2022-23 | K18: Change 2015-16 to 2022-23
A19: Bihar | B19: 6356.7 | C19: 6802.2 | D19: 8239.3 | E19: 8093.1 | F19: 6155.5 | G19: 6298 | H19: 6747 | I19: 7717 | J19: 6725.2 | K19: =J19/C19-1 -> -0.011319867
A20: Haryana | B20: 4006 | C20: 4145 | D20: 4453 | E20: 4523.38 | F20: 4516.1 | G20: 4824.3 | H20: 4424.9 | I20: 4618 | J20: 5406.9 | K20: =J20/C20-1 -> 0.30443908
A21: Karnataka | B21: 3541 | C21: 3021 | D21: 2604.8 | E21: 3017.1 | F21: 3431 | G21: 3634.5 | H21: 4291.8 | I21: 4318.4 | J21: 4001.3 | K21: =J21/C21-1 -> 0.3244952
A22: Madhya Pradesh | B22: 3625.3 | C22: 3546.7 | D22: 4226.8 | E22: 4123.9 | F22: 4494.7 | G22: 4778.2 | H22: 4413.8 | I22: 4814.9 | J22: 7657.2 | K22: =J22/C22-1 -> 1.1589647
A23: Maharashtra | B23: 2946 | C23: 2593 | D23: 3109.5 | E23: 2730.8 | F23: 3275.7 | G23: 2897.6 | H23: 3291.7 | I23: 3598.1 | J23: 3899.1 | K23: =J23/C23-1 -> 0.50370228
A24: Punjab | B24: 11107 | C24: 11823 | D24: 11586.2 | E24: 13381.79 | F24: 12821.6 | G24: 11779.3 | H24: 12783.7 | I24: 12885.5 | J24: 13146.7 | K24: =J24/C24-1 -> 0.11195974
A25: Rajasthan | B25: 366.7 | C25: 369.8 | D25: 452.7 | E25: 450.87 | F25: 453.2 | G25: 480.5 | H25: 634 | I25: 478.6 | J25: 577.4 | K25: =J25/C25-1 -> 0.56138453
A26: Tamil Nadu | B26: 5727.8 | C26: 7517.1 | D26: 2369.4 | E26: 6638.9 | F26: 6130.9 | G26: 7171.1 | H26: 6881.2 | I26: 7906.6 | J26: 7850.6 | K26: =J26/C26-1 -> 0.044365513
A27: Telangana | B27: 4440.8 | C27: 3047 | D27: 5173.4 | E27: 6262.2 | F27: 6670 | G27: 7427.8 | H27: 10217.1 | I27: 12409.6 | J27: 16013.9 | K27: =J27/C27-1 -> 4.2556285
A28: Uttar Pradesh | B28: 12167.9 | C28: 12501 | D28: 13754 | E28: 13274 | F28: 15545.3 | G28: 15517.8 | H28: 15520 | I28: 15271.5 | J28: 15171.3 | K28: =J28/C28-1 -> 0.21360691
A29: All India | B29: 104798.5 | C29: 104408.2 | D29: 109698.4 | E29: 112757.6 | F29: 116477.8 | G29: 118870.3 | H29: 124368.3 | I29: 129471.4 | J29: 135542 | K29: =J29/C29-1 -> 0.29819305
A30: Source: RBI Handbook 2023, Table 60 (Ministry of Agriculture). Gap: 2023-24 and 2024-25 state values.

Sheet Coarse_cereals
A1: Coarse cereals area by state (maize + jowar + bajra + ragi + small millets + barley)
A2: Maize cannot be separated from millets in this table; state maize data is in the Gaps tab.
A4: Area ('000 ha), RBI T71 | B4: 2014-15 | C4: 2015-16 | D4: 2016-17 | E4: 2017-18 | F4: 2018-19 | G4: 2019-20 | H4: 2020-21 | I4: 2021-22 | J4: 2022-23 | K4: Change 2015-16 to 2022-23
A5: Bihar | B5: 732.7 | C5: 730 | D5: 745.1 | E5: 702.2 | F5: 699.8 | G5: 689.2 | H5: 667.1 | I5: 678.28 | J5: 671.87 | K5: =J5/C5-1 -> -0.079630137
A6: Haryana | B6: 474 | C6: 458 | D6: 565 | E6: 524 | F6: 485.8 | G6: 540.8 | H6: 616.4 | I6: 514.75 | J6: 573.2 | K6: =J6/C6-1 -> 0.25152838
A7: Karnataka | B7: 3349 | C7: 3223 | D7: 3179 | E7: 3438 | F7: 3013.2 | G7: 3262.6 | H7: 3509 | I7: 3230.4 | J7: 3302 | K7: =J7/C7-1 -> 0.024511325
A8: Madhya Pradesh | B8: 1794 | C8: 1848 | D8: 2086.6 | E8: 2211 | F8: 1841 | G8: 1921.9 | H8: 1947 | I8: 1971 | J8: 2085 | K8: =J8/C8-1 -> 0.12824675
A9: Maharashtra | B9: 5423 | C9: 5254 | D9: 5211.7 | E9: 4242.3 | F9: 3320 | G9: 4223.9 | H9: 4130.2 | I9: 3707.93 | J9: 3379.6 | K9: =J9/C9-1 -> -0.35675676
A10: Punjab | B10: 137 | C10: 124 | D10: 125.5 | E10: 122.7 | F10: 116.9 | G10: 121.3 | H10: 114.1 | I10: 111.4 | J10: 101.3 | K10: =J10/C10-1 -> -0.18306452
A11: Rajasthan | B11: 5986.5 | C11: 5818.3 | D11: 5938.9 | E11: 5906.6 | F11: 5825.8 | G11: 6132.5 | H11: 6177.4 | I11: 5514.98 | J11: 6481.03 | K11: =J11/C11-1 -> 0.11390441
A12: Tamil Nadu | B12: 859.3 | C12: 867.2 | D12: 718 | E12: 885 | F12: 924.1 | G12: 961.4 | H12: 980.4 | I12: 954.69 | J12: 922.18 | K12: =J12/C12-1 -> 0.063399446
A13: Telangana | B13: 784 | C13: 657 | D13: 911 | E13: 707 | F13: 608 | G13: 661 | H13: 361 | I13: 486.1 | J13: 582.7 | K13: =J13/C13-1 -> -0.1130898
A14: Uttar Pradesh | B14: 2010 | C14: 1966 | D14: 2008 | E14: 1971 | F14: 1914 | G14: 1989 | H14: 2023 | I14: 1995 | J14: 2021 | K14: =J14/C14-1 -> 0.027975585
A15: All India | B15: 25169.8 | C15: 24389.3 | D15: 25007.6 | E15: 24286.5 | F15: 22145.7 | G15: 23987.9 | H15: 24117.8 | I15: 22700.23 | J15: 23588.67 | K15: =J15/C15-1 -> -0.0328271
A16: Source: RBI Handbook 2023, Table 71 (Ministry of Agriculture). 2022-23 = 3rd advance estimate.

Sheet National_production
A1: All-India production by crop (lakh tonnes)
A2: Ragi = kharif only. 2025-26 = 3rd advance estimate.
A4: Year | B4: Rice | C4: Wheat | D4: Maize | E4: Jowar | F4: Bajra | G4: Ragi | H4: Sugarcane | I4: Status
A5: 2015-16 | B5: 1044.08 | C5: 922.88 | D5: 225.67 | E5: 42.38 | F5: 80.67 | G5: 18.22 | H5: 3484.48 | I5: final
A6: 2016-17 | B6: 1096.98 | C6: 985.1 | D6: 259 | E6: 45.68 | F6: 97.3 | G6: 13.85 | H6: 3060.69 | I6: final
A7: 2017-18 | B7: 1127.58 | C7: 998.7 | D7: 287.53 | E7: 48.03 | F7: 92.09 | G7: 19.85 | H7: 3799.05 | I7: final
A8: 2018-19 | B8: 1164.78 | C8: 1035.96 | D8: 277.15 | E8: 34.75 | F8: 86.64 | G8: 12.39 | H8: 4054.16 | I8: final
A9: 2019-20 | B9: 1188.7 | C9: 1078.61 | D9: 287.66 | E9: 47.72 | F9: 103.63 | G9: 17.55 | H9: 3705 | I9: final
A10: 2020-21 | B10: 1243.68 | C10: 1095.86 | D10: 316.47 | E10: 48.12 | F10: 108.63 | G10: 19.98 | H10: 4053.99 | I10: final
A11: 2021-22 | B11: 1294.71 | C11: 1077.42 | D11: 337.3 | E11: 41.51 | F11: 97.81 | G11: 17.01 | H11: 4394.25 | I11: final
A12: 2022-23 | B12: 1357.55 | C12: 1105.54 | D12: 380.85 | E12: 38.14 | F12: 114.31 | G12: 16.91 | H12: 4905.33 | I12: final
A13: 2023-24 | B13: 1378.25 | C13: 1132.92 | D13: 376.65 | E13: 47.37 | F13: 107.16 | G13: 16.7 | H13: 4531.58 | I13: final
A14: 2024-25 | B14: 1501.84 | C14: 1179.45 | D14: 434.09 | E14: 49.55 | F14: 112.05 | G14: 19.77 | H14: 4546.11 | I14: final
A15: 2025-26 | B15: 1540.24 | C15: 1206.57 | D15: 550.93 | E15: 43.56 | F15: 108.48 | G15: 20 | H15: 5000.63 | I15: 3rd AE
A16: Change 2015-16 to 2024-25 | B16: =B14/B5-1 -> 0.43843384 | C16: =C14/C5-1 -> 0.27801014 | D16: =D14/D5-1 -> 0.92356095 | E16: =E14/E5-1 -> 0.16918358 | F16: =F14/F5-1 -> 0.38899219 | G16: =G14/G5-1 -> 0.08507135 | H16: =H14/H5-1 -> 0.30467387
A18: Source: DES, Ministry of Agriculture, Time Series of 3rd Advance Estimates 2025-26 (as on 27 May 2026).

Sheet MSP_FRP
A1: Minimum support prices and sugarcane FRP (Rs per quintal)
A2: Kharif crops by marketing season; wheat by crop year (marketed in the following rabi season); FRP by sugar season.
A4: Crop | B4: Basis | C4: 2015-16 | D4: 2016-17 | E4: 2017-18 | F4: 2018-19 | G4: 2019-20 | H4: 2020-21 | I4: 2021-22 | J4: 2022-23 | K4: 2023-24 | L4: 2024-25 | M4: 2025-26 | N4: Change 2015-16 to 2024-25 | O4: Step-up 2018-19 vs 2017-18
A5: Paddy (common) | B5: KMS | C5: 1410 | D5: 1470 | E5: 1550 | F5: 1750 | G5: 1815 | H5: 1868 | I5: 1940 | J5: 2040 | K5: 2183 | L5: 2300 | M5: 2369 | N5: =L5/C5-1 -> 0.63120567 | O5: =F5/E5-1 -> 0.12903226
A6: Maize | B6: KMS | C6: 1325 | D6: 1365 | E6: 1425 | F6: 1700 | G6: 1760 | H6: 1850 | I6: 1870 | J6: 1962 | K6: 2090 | L6: 2225 | M6: 2400 | N6: =L6/C6-1 -> 0.67924528 | O6: =F6/E6-1 -> 0.19298246
A7: Jowar (hybrid) | B7: KMS | C7: 1570 | D7: 1625 | E7: 1700 | F7: 2430 | G7: 2550 | H7: 2620 | I7: 2738 | J7: 2970 | K7: 3180 | L7: 3371 | M7: 3699 | N7: =L7/C7-1 -> 1.1471338 | O7: =F7/E7-1 -> 0.42941176
A8: Bajra | B8: KMS | C8: 1275 | D8: 1330 | E8: 1425 | F8: 1950 | G8: 2000 | H8: 2150 | I8: 2250 | J8: 2350 | K8: 2500 | L8: 2625 | M8: 2775 | N8: =L8/C8-1 -> 1.0588235 | O8: =F8/E8-1 -> 0.36842105
A9: Ragi | B9: KMS | C9: 1650 | D9: 1725 | E9: 1900 | F9: 2897 | G9: 3150 | H9: 3295 | I9: 3377 | J9: 3578 | K9: 3846 | L9: 4290 | M9: 4886 | N9: =L9/C9-1 -> 1.6 | O9: =F9/E9-1 -> 0.52473684
A10: Tur (arhar) | B10: KMS | C10: 4625 | D10: 5050 | E10: 5450 | F10: 5675 | G10: 5800 | H10: 6000 | I10: 6300 | J10: 6600 | K10: 7000 | L10: 7550 | M10: 8000 | N10: =L10/C10-1 -> 0.63243243 | O10: =F10/E10-1 -> 0.041284404
A11: Moong | B11: KMS | C11: 4850 | D11: 5225 | E11: 5575 | F11: 6975 | G11: 7050 | H11: 7196 | I11: 7275 | J11: 7755 | K11: 8558 | L11: 8682 | M11: 8768 | N11: =L11/C11-1 -> 0.79010309 | O11: =F11/E11-1 -> 0.25112108
A12: Urad | B12: KMS | C12: 4625 | D12: 5000 | E12: 5400 | F12: 5600 | G12: 5700 | H12: 6000 | I12: 6300 | J12: 6600 | K12: 6950 | L12: 7400 | M12: 7800 | N12: =L12/C12-1 -> 0.6 | O12: =F12/E12-1 -> 0.037037037
A13: Wheat | B13: crop year (RMS = next year) | C13: 1525 | D13: 1625 | E13: 1735 | F13: 1840 | G13: 1925 | H13: 1975 | I13: 2015 | J13: 2125 | K13: 2275 | L13: 2425 | M13: 2585 | N13: =L13/C13-1 -> 0.59016393 | O13: =F13/E13-1 -> 0.060518732
A14: Sugarcane FRP | B14: sugar season | C14: 230 | D14: 230 | E14: 255 | F14: 275 | G14: 275 | H14: 285 | I14: 290 | J14: 305 | K14: 315 | L14: 340 | M14: 355 | N14: =L14/C14-1 -> 0.47826087 | O14: =F14/E14-1 -> 0.078431373
A15: FRP base recovery % | B15: sugar season | C15: 9.5 | D15: 9.5 | E15: 9.5 | F15: 10 | G15: 10 | H15: 10 | I15: 10 | J15: 10.25 | K15: 10.25 | L15: 10.25 | M15: 10.25
A16: FRP is fixed for a base recovery rate that rose from 9.5% to 10% (2018-19) and 10.25% (2022-23). At 9.5% recovery the 2024-25 floor was Rs 315.10, a 37.0% rise on 2015-16, not 47.8%.
A17: Sources: DES MSP statement (12 Dec 2025) for 2021-22 onward; CACP/Government MSP compilation (S.P. University copy) for 2015-16 to 2020-21; FRP base rates from Cabinet decisions (see Source_Log).

Sheet Ethanol
A1: National ethanol series (ethanol supply years)
A2: ESY ran Dec-Nov until 2021-22, then Nov-Oct. Blended and supplied volumes are different measures.
A4: ESY | B4: Blended (crore L) | C4: Blending % | D4: Supplied (crore L) | E4: Source | F4: Note
A5: 2013-14 | B5: 38 | C5: 0.0153 | E5: Lok Sabha AU2832 (8 Aug 2024)
A6: 2018-19 | B6: 188.6 | C6: 0.05 | E6: MoPNG website (Ethanol Blended Petrol page)
A7: 2019-20 | F7: not found in an official source yet
A8: 2020-21 | B8: 302.3 | C8: 0.0817 | E8: Lok Sabha reply (via Indian Chemical News 9 Aug 2024) | F8: Dataful (MoPNG) shows 332 crore L / 8.5%
A9: 2021-22 | B9: 433.6 | C9: 0.1 | E9: Dataful dataset 21604 (MoPNG); 10% reached Jun 2022 per MoPNG
A10: 2022-23 | B10: 508.5 | C10: 0.1206 | E10: Lok Sabha AU2832 (12.06%); volume Dataful 21604 | F10: 11-month year (Dec-Oct)
A11: 2023-24 | B11: 707.4 | C11: 0.146 | D11: 672.49 | E11: Blending %: MoPNG (iamrenew 18 Apr 2025); blended volume: Dataful 21604; supplied: Indian Express Oct 2025 | F11: blended vs supplied differ
A12: 2024-25 | B12: 1022.4 | C12: 0.192 | D12: 1039 | E12: PPAC via BioEnergy Times 20 Nov 2025 (blended); AIDA via Outlook Business 20 Feb 2026 (supplied) | F12: 20% first reached Oct 2025
A14: ESY | B14: Feedstock | C14: Value | D14: Unit | E14: Source
A15: 2023-24 | B15: Total supplied | C15: 672.49 | D15: crore L | E15: Indian Express (Oct 2025) via Vision IAS
A16: 2023-24 | B16: Grain-based | C16: 402.22 | D16: crore L | E16: Indian Express (Oct 2025) via Vision IAS
A17: 2023-24 | B17: of which maize | C17: 286.47 | D17: crore L | E17: Indian Express (Oct 2025) via Vision IAS
A18: 2023-24 | B18: of which broken/damaged grain | C18: 115.62 | D18: crore L | E18: Indian Express (Oct 2025) via Vision IAS
A19: 2023-24 | B19: Sugarcane-based | C19: 270.27 | D19: crore L | E19: Indian Express (Oct 2025) via Vision IAS
A20: 2023-24 | B20: Maize share | C20: 42.74 | D20: % | E20: Down To Earth 14 Aug 2025
A21: 2024-25 | B21: Total supplied | C21: 1039 | D21: crore L | E21: AIDA via Outlook Business 20 Feb 2026
A22: 2024-25 | B22: Grain-based | C22: 718 | D22: crore L | E22: AIDA via Outlook Business 20 Feb 2026
A23: 2024-25 | B23: Sugarcane-based | C23: 321 | D23: crore L | E23: AIDA via Outlook Business 20 Feb 2026
A24: 2024-25 | B24: Maize share | C24: 48-51 | D24: % | E24: AIDA via Outlook Business 20 Feb 2026
A25: 2021-22 | B25: Maize share | C25: 0 | D25: % | E25: Rajya Sabha reply MoS Petroleum 20 Jul 2026 (ANI)
A26: 2025-26 | B26: Maize share | C26: ~37 | D26: % | E26: Rajya Sabha reply MoS Petroleum 20 Jul 2026 (ANI)
A27: 2023-24 | B27: Sugar diversion cap | C27: 1.7 | D27: million t | E27: DFPD directive 15 Dec 2023 via Argus Media
B28: Grain share 2023-24 (computed) | C28: =C16/C15 -> 0.59810555
B29: Grain share 2024-25 (computed) | C29: =C22/C21 -> 0.69104909
B30: Maize share 2023-24 (computed) | C30: =C17/C15 -> 0.42598403
A32: Period | B32: Feedstock | C32: Price | D32: Unit | E32: Source
A33: 2023-24 | B33: C-heavy molasses | C33: 56.58 | D33: Rs per L | E33: CCEA decision Jan 2025 (Khan Global summary)
A34: 2024-25 | B34: C-heavy molasses | C34: 57.97 | D34: Rs per L | E34: CCEA decision Jan 2025 (Khan Global summary)
A35: 2024-25 | B35: B-heavy molasses | C35: 60.73 | D35: Rs per L | E35: CCEA decision Jan 2025 (Khan Global summary)
A36: 2024-25 | B36: Cane juice / sugar / syrup | C36: 65.61 | D36: Rs per L | E36: CCEA decision Jan 2025 (Khan Global summary)
A37: 2022-23 | B37: Maize (from 22 Aug 2023) | C37: 66.07 | D37: Rs per L | E37: Lok Sabha AU755 (7 Feb 2024)
A38: 2023-24 | B38: Maize | C38: 71.86 | D38: Rs per L | E38: Lok Sabha AU755 (7 Feb 2024)
A39: 2020 | B39: FCI rice to distilleries | C39: 2250 | D39: Rs per quintal | E39: Policy Circle (28 Jul 2023)
A40: Dec 2020 | B40: FCI rice to distilleries | C40: 2000 | D40: Rs per quintal | E40: Policy Circle (28 Jul 2023)
A41: 2024-25 (before Jan 2025) | B41: FCI rice reserve price | C41: 2800 | D41: Rs per quintal | E41: iamrenew (21 Jan 2025)
A42: 2024-25 (from Jan 2025) | B42: FCI rice reserve price | C42: 2250 | D42: Rs per quintal | E42: iamrenew (21 Jan 2025)
A44: Item | B44: Period | C44: Value | D44: Unit | E44: Source
A45: Forex saved | B45: ESY 2018-19 | C45: 5500 | D45: Rs crore | E45: Lok Sabha AU2832 (8 Aug 2024)
A46: Forex saved | B46: ESY 2019-20 | C46: 3500 | D46: Rs crore | E46: Lok Sabha AU2832 (8 Aug 2024)
A47: Forex saved | B47: ESY 2020-21 | C47: 10100 | D47: Rs crore | E47: Lok Sabha AU2832 (8 Aug 2024)
A48: Forex saved | B48: ESY 2021-22 | C48: 22500 | D48: Rs crore | E48: Lok Sabha AU2832 (8 Aug 2024)
A49: Forex saved | B49: ESY 2022-23 | C49: 24300 | D49: Rs crore | E49: Lok Sabha AU2832 (8 Aug 2024)
A50: FCI rice sold to distilleries (cumulative) | B50: Dec 2020 to Jul 2023 | C50: >24 | D50: lakh t | E50: Policy Circle (28 Jul 2023)
A51: FCI rice cap for distilleries | B51: Aug-Oct 2024 | C51: 23 | D51: lakh t | E51: Deccan Herald / PTI (29 Aug 2024)
A52: FCI rice cap for distilleries | B52: ESY 2024-25 | C52: 24 | D52: lakh t | E52: iamrenew (21 Jan 2025)
A53: Grain distilleries (number) | B53: Dec 2023 | C53: 155 | D53: count | E53: Lok Sabha AU632 (6 Dec 2023)
A54: Grain distillery capacity | B54: Dec 2023 | C54: 505 | D54: crore L per year | E54: Lok Sabha AU632 (6 Dec 2023)
A55: Ethanol demand projection | B55: 2025-26 | C55: 1016 | D55: crore L | E55: NITI Aayog roadmap (Jun 2021)
A56: Capacity needed | B56: 2025-26 | C56: 1500 (740 grain / 760 sugar) | D56: crore L | E56: NITI Aayog roadmap (Jun 2021)
A57: Water per L of sugar-based ethanol (roadmap) | B57: - | C57: 2860 | D57: L water per L | E57: NITI Aayog roadmap via PRS
A58: Process water in distillery | B58: - | C58: 3-5 | D58: L water per L | E58: MoPNG / Rajya Sabha 20 Jul 2026
A59: Ethanol yield from rice | B59: - | C59: ~470 | D59: L per t | E59: Kisan Tak report via National Herald (Apr 2026)
A60: Ethanol yield from cane juice | B60: - | C60: 70-81 | D60: L per t cane | E60: Jha et al. 2026 PLOS ONE (citing empirical estimates)
A61: Social cost of carbon (global median) | B61: 2018 | C61: 417 (177-805) | D61: US$ per t CO2 | E61: Ricke et al. 2018 Nature Climate Change
A63: Conflicts kept: 2020-21 blended 302.3 crore L / 8.17% (Lok Sabha) vs 332 / 8.5% (Dataful); maize share 2024-25 48-51% (AIDA) vs ~37% for 2025-26 (Rajya Sabha).

Sheet Source_Log
A1: Source log
A2: Every source was opened and checked on 25 Oct 2026. Type: Official / Official via media / Compiled official / Institutional / Media.
A4: Tab | B4: Data | C4: Document / table | D4: Original agency | E4: Type | F4: URL | G4: Note
A5: Groundwater | B5: Stage of extraction, extraction, resource 2017-2024 | C5: RBI Handbook 2024-25, Table 107 (11 Dec 2025) | D5: CGWB, Ministry of Jal Shakti | E5: Compiled official | F5: https://rbi.org.in/ScriptS/PublicationsView.aspx?id=23556 | G5: Punjab 2022 conflict noted
A6: Groundwater | B6: Punjab 2017-2024 stage of extraction | C6: Dynamic Ground Water Resources & Quality of Punjab, 2024 | D6: CGWB | E6: Official | F6: https://cgwb.gov.in/cgwbpnm/public/uploads/documents/1742295732461871757file.pdf | G6: Used for Punjab 2022 correction
A7: Groundwater | B7: 2017 and 2020 extraction totals (cross-check) | C7: Lok Sabha AU3018 | D7: Ministry of Jal Shakti | E7: Official | F7: https://eparlib.sansad.in/bitstream/123456789/1059876/1/AU3018.pdf | G7: Matches RBI exactly
A8: Groundwater | B8: Bihar 2024 extraction by use (10.21 irrigation of 14.09 bcm) | C8: Dynamic Ground Water Resources of Bihar, 2024 | D8: CGWB / Govt of Bihar | E8: Official | F8: https://www.cgwb.gov.in/cgwbpnm/public/uploads/documents/1743584819841710360file.pdf | G8: Example of state split; others pending
A9: Rainfall | B9: Monsoon rainfall 2013-2016 | C9: Lok Sabha US 4446 (14 Dec 2016) | D9: MoES / IMD | E9: Official | F9: https://moes.gov.in/sites/default/files/LS_US_4446_14122016.pdf | G9: 2015, 2016 used
A10: Rainfall | B10: Monsoon and annual rainfall 2018-2020 | C10: Rajya Sabha 165 (3 Aug 2021) | D10: MoES / IMD | E10: Official | F10: https://www.moes.gov.in/sites/default/files/RS-English-165-03082021.pdf | G10: 2020 rows misaligned; not used
A11: Rainfall | B11: Monsoon rainfall 2020-2022 | C11: Rajya Sabha 25 (27 Jul 2023) | D11: MoES / IMD | E11: Official | F11: https://www.moes.gov.in/sites/default/files/RS-in-25-27-07-2023.pdf
A12: Sugarcane | B12: Area 2014-15 to 2022-23 | C12: RBI Handbook 2023, Table 80 | D12: Ministry of Agriculture | E12: Compiled official | F12: https://rbi.org.in/Scripts/PublicationsView.aspx?id=22144
A13: Sugarcane | B13: Area, production, yield 2018-19 to 2023-24 | C13: State-wise APY of sugarcane (StatisticsAPY-23-24) | D13: ICAR-SBI citing DES | E13: Official | F13: https://sugarcane.icar.gov.in/wp-content/uploads/2024/08/StatisticsAPY-23-24.pdf | G13: 2023-24 = 2nd AE
A14: Sugarcane | B14: Yield 2015-16 to 2018-19 | C14: Lok Sabha AU1760 (2 Jul 2019) | D14: Ministry of Agriculture | E14: Official | F14: https://eparlib.nic.in/bitstream/123456789/951428/1/AU1760.pdf
A15: Sugarcane | B15: Area 2013-14 to 2017-18 (cross-check) | C15: Lok Sabha AU443 (5 Feb 2019) | D15: Ministry of Agriculture | E15: Official | F15: https://eparlib.nic.in/bitstream/123456789/806271/1/AU443.pdf | G15: Matches RBI T80
A16: UPAg_crops | B16: State area and production by crop and season, 2016-17 to 2025-26 | C16: UPAg State Profile: Crop-wise APY (dash.upag.gov.in/stateprofile) | D16: DA&FW / DES, Ministry of Agriculture | E16: Official | F16: https://upag.gov.in/dash-reports/stateprofile | G16: Read via browser; 2025-26 = 3rd advance estimate; All India matches DES time series
A17: Rice | B17: Area 2004-05 to 2022-23 | C17: RBI Handbook 2023, Table 69 | D17: Ministry of Agriculture | E17: Compiled official | F17: https://www.rbi.org.in/Scripts/PublicationsView.aspx?id=22133
A18: Rice | B18: Production 2014-15 to 2022-23 | C18: RBI Handbook 2023, Table 60 | D18: Ministry of Agriculture | E18: Compiled official | F18: https://www.rbi.org.in/Scripts/PublicationsView.aspx?id=22124
A19: Coarse_cereals | B19: Area 2014-15 to 2022-23 | C19: RBI Handbook 2023, Table 71 | D19: Ministry of Agriculture | E19: Compiled official | F19: https://rbi.org.in/scriptS/PublicationsView.aspx?id=22135
A20: National_production | B20: All-India production 2015-16 to 2025-26 | C20: Time Series, 3rd Advance Estimates 2025-26 | D20: DES, Ministry of Agriculture | E20: Official | F20: https://desagri.gov.in/wp-content/uploads/2026/06/Time-Series-3rd-AE-2025-26-English.pdf
A21: MSP_FRP | B21: MSP 2021-22 to 2025-26 | C21: MSP statement as on 12 Dec 2025 | D21: DES / CACP | E21: Official | F21: https://desagri.gov.in/wp-content/uploads/2025/12/MSP-Statement_English_As-on-12.12.2025.pdf
A22: MSP_FRP | B22: MSP and FRP 2012-13 to 2021-22 | C22: MSP recommended by CACP and fixed by Government | D22: CACP / Government of India | E22: Compiled official | F22: https://www.spuvvn.edu/academic_centres/c_c_s/MSP_SINCE_2012_13.pdf | G22: Matches DES for overlapping 2021-22
A23: MSP_FRP | B23: FRP 2015-16 at 9.5% recovery | C23: Cabinet decision, 16 Jan 2015 (report) | D23: CCEA | E23: Official via media | F23: https://www.ap7am.com/en/6592/centre-raises-sugarcane-price-to-rs230-per-quintal
A24: MSP_FRP | B24: FRP 2017-18 at 9.5% recovery | C24: Cabinet decision, 24 May 2017 (report) | D24: CCEA | E24: Official via media | F24: https://www.millenniumpost.in/nation/nation-243599
A25: MSP_FRP | B25: FRP 2018-19 to 2022-23 base rates (10%, then 10.25%) | C25: Business Standard topic page, Cabinet decisions | D25: CCEA | E25: Official via media | F25: https://www.business-standard.com/topic/sugarcane-frp
A26: MSP_FRP | B26: FRP 2024-25 Rs 340 at 10.25%; Rs 315.10 at 9.5% | C26: Cabinet decision Feb 2024 | D26: CCEA | E26: Official | F26: https://www.narendramodi.in/cabinet-approves-frp-of-sugarcane-payable-by-sugar-factories-for-sugar-season-2024-25
A27: MSP_FRP | B27: FRP 2025-26 Rs 355 at 10.25% | C27: Cabinet decision 30 Apr 2025 (PTI) | D27: CCEA | E27: Official via media | F27: https://www.theweek.in/wire-updates/business/2025/04/30/del51-cab-sugarcane.html
A28: Ethanol | B28: Blending 2013-14 and 2022-23; forex savings | C28: Lok Sabha AU2832 (8 Aug 2024) | D28: MoPNG | E28: Official | F28: https://eparlib.nic.in/bitstream/123456789/2980100/1/AU2832_aKas3t.pdf
A29: Ethanol | B29: ESY 2018-19 procurement and blending | C29: Ethanol Blended Petrol page | D29: MoPNG | E29: Official | F29: https://mopng.gov.in/en/refining/ethanol-blended-petrol
A30: Ethanol | B30: ESY 2020-21 302.3 crore L, 8.17% | C30: Lok Sabha reply reported 9 Aug 2024 | D30: MoPNG | E30: Official via media | F30: https://www.indianchemicalnews.com/general/lite/increase-in-blending-of-ethanol-22815
A31: Ethanol | B31: Blended volumes 2020-21 to 2024-25 | C31: Dataful dataset 21604 | D31: MoPNG (per Dataful) | E31: Compiled official | F31: https://dataful.in/datasets/21604/ | G31: Secondary; used where Parliament gives no volume
A32: Ethanol | B32: ESY 2023-24 % blending; 20% announcement | C32: iamrenew, 18 Apr 2025 | D32: MoPNG | E32: Official via media | F32: https://www.iamrenew.com/green-energy/india-achieves-20-ethanol-blending-sets-sight-on-30-by-2030/
A33: Ethanol | B33: ESY 2024-25 average 19.2%, 1,022.4 crore L | C33: BioEnergy Times, 20 Nov 2025 | D33: PPAC | E33: Official via media | F33: https://bioenergytimes.com/esy-2024-25-india-achieves-20-ethanol-blending-in-october/
A34: Ethanol | B34: ESY 2023-24 feedstock split | C34: Indian Express explainer via Vision IAS (13 Oct 2025) | D34: Not named | E34: Media | F34: https://visionias.in/current-affairs/upsc-daily-news-summary/article/2025-10-13/the-indian-express/economy/how-grain-not-sugar-is-fuelling-indias-ethanol-production | G34: Trace to MoPNG in Stage 3
A35: Ethanol | B35: ESY 2024-25 feedstock split | C35: Outlook Business, 20 Feb 2026 | D35: AIDA | E35: Media (industry data) | F35: https://www.outlookbusiness.com/industry/maize-leads-esy-2024-25-ethanol-feedstock-shift | G35: Industry body figures
A36: Ethanol | B36: Maize share 0% (2021-22) to ~37% (2025-26) | C36: Rajya Sabha reply 20 Jul 2026 (ANI) | D36: MoPNG | E36: Official via media | F36: https://thedailyguardian.com/business/centre-assures-20-ethanol-blending-target-has-no-impact-on-indias-food-security-or-water-stress20260720183632-739371/
A37: Ethanol | B37: Maize share 42.74% (2023-24) | C37: Down To Earth, 14 Aug 2025 | D37: Not named | E37: Media | F37: https://www.downtoearth.org.in/agriculture/biofuels-area-under-maize-cultivation-in-india-increases-sharply-driven-by-push-for-ethanol
A38: Ethanol | B38: Molasses and juice ethanol prices 2023-24, 2024-25 | C38: CCEA decision Jan 2025 (summary) | D38: CCEA | E38: Official via media | F38: https://currentaffairs.khanglobalstudies.com/cabinet-approves-revised-ethanol-procurement-price-for-ebp-programme-2024-25/ | G38: Replace with PIB original
A39: Ethanol | B39: Maize ethanol prices 2022-23, 2023-24 | C39: Lok Sabha AU755 (7 Feb 2024) | D39: DFPD | E39: Official | F39: https://eparlib.nic.in/bitstream/123456789/2974643/1/AU755.pdf
A40: Ethanol | B40: FCI rice prices and quantities 2020-2023 | C40: Policy Circle explainer, 28 Jul 2023 | D40: FCI / DFPD | E40: Media | F40: https://www.policycircle.org/economy/fci-rice-for-ethanol-explainer/
A41: Ethanol | B41: FCI rice resumed Aug 2024, 23 lakh t | C41: Deccan Herald (PTI), 29 Aug 2024 | D41: DFPD | E41: Official via media | F41: https://www.deccanherald.com/amp/story/business%2Fgovt-allows-sale-of-23-lakh-tonnes-of-rice-from-food-corporation-of-indias-stock-to-ethanol-makers-3169620
A42: Ethanol | B42: FCI rice Rs 2,250/qtl, 24 lakh t, 2024-25 | C42: iamrenew, 21 Jan 2025 | D42: DFPD (OMSS-D policy) | E42: Official via media | F42: https://www.iamrenew.com/green-energy/govt-allows-fci-to-sell-rice-to-ethanol-makers-at-rs-22-5-kg-tender-for-110-crore-liters-to-follow-soon/
A43: Ethanol | B43: Sugar diversion cap 1.7 Mt (2023-24) | C43: Argus Media | D43: DFPD | E43: Official via media | F43: https://www.argusmedia.com/en/news/2520022-india-eases-curbs-on-use-of-sugarcane-juice-for-ethanol
A44: Ethanol | B44: Grain distilleries 155, capacity ~505 crore L | C44: Lok Sabha AU632 (6 Dec 2023) | D44: DFPD | E44: Official | F44: https://eparlib.nic.in/bitstream/123456789/2972007/1/AU632.pdf
A45: Ethanol | B45: Roadmap demand, capacity, 2,860 L water per L | C45: NITI Aayog roadmap (Jun 2021) / PRS summary | D45: NITI Aayog, MoPNG | E45: Official | F45: https://prsindia.org/policy/report-summaries/report-of-niti-aayog-on-roadmap-for-ethanol-blending-in-india-2020-25
A46: Ethanol | B46: Rice ethanol yield ~470 L/t | C46: National Herald (Kisan Tak report), Apr 2026 | D46: Not named | E46: Media | F46: https://www.nationalheraldindia.com/amp/story/national/10000-litres-of-water-for-a-litre-of-fuel-india-govts-ethanol-push-under-scrutiny | G46: Verify in Stage 3
A47: Ethanol | B47: Cane juice ethanol yield 70-81 L/t | C47: Jha et al. 2026, PLOS ONE | D47: Peer-reviewed | E47: Peer-reviewed | F47: https://journals.plos.org/plosone/article?id=10.1371%2Fjournal.pone.0351419
A48: Ethanol | B48: Social cost of carbon US$417/t | C48: Ricke et al. 2018, Nature Climate Change | D48: Peer-reviewed | E48: Peer-reviewed | F48: https://carnegiescience.edu/country-level-social-cost-carbon
A49: Analysis_Stage4 | B49: Rabi maize irrigation: 5 irrigations x 6 cm | C49: Bharati et al. 2007, Indian Journal of Agronomy 52(1) | D49: Peer-reviewed | E49: Peer-reviewed | F49: https://pub.isa-india.in/index.php/ija/article/view/4883 | G49: Pusa, Bihar
A50: Analysis_Stage4 | B50: Spring maize PET 693-955 mm | C50: Majumder, Kingra & Singh 2016, Annals of Agricultural Research 37(2) | D50: Peer-reviewed | E50: Peer-reviewed | F50: https://epubs.icar.org.in/index.php/AAR/article/view/61910 | G50: Ludhiana, 1985-2014
A51: Analysis_Stage4 | B51: Spring maize needs 18+ irrigations; Punjab 1.46 lakh ha spring/summer maize; planned curbs | C51: The Tribune, Jun 2025 (PAU, Punjab Agriculture Dept) | D51: Punjab Agriculture Dept / PAU | E51: Media | F51: https://www.tribuneindia.com/news/punjab/agri-dept-plans-to-impose-curbs-on-spring-maize-in-punjab-629882/amp | G51: Not reflected in UPAg Punjab summer maize
A52: Analysis_Stage4 | B52: Groundwater share of net irrigated area (tube wells 45%, other wells 16%), 2011-12 | C52: Statistical Year Book India, Irrigation chapter | D52: MoSPI | E52: Official | F52: https://www.mospi.gov.in/sites/default/files/Statistical_year_book_india_chapters/Irrigation.pdf | G52: Old; national only
A53: Analysis_Stage4 | B53: Micro-irrigation water savings 20-48%; 115 lakh ha under PDMC (Jul 2026) | C53: PIB backgrounder, Aug 2026 (citing Economic Survey 2020-21) | D53: PIB / DA&FW | E53: Official | F53: https://static.pib.gov.in/WriteReadData/specificdocs/documents/2026/aug/doc_9732_20260829_12330401.pdf
A54: Analysis_Stage4 | B54: CGWA 2020 guidelines: NOC for industry, no new industry in over-exploited units, farmers exempt | C54: Drishti IAS summary of Rajya Sabha TV, 29 Oct 2020 | D54: CGWA, Ministry of Jal Shakti | E54: Official via media | F54: https://www.drishtiias.com/loksabha-rajyasabha-discussions/groundwater-extraction-norms/print_manually
A55: Analysis_Stage4 | B55: Distillery process water 3-5 L per L | C55: Rajya Sabha reply, 20 Jul 2026 (ANI) | D55: MoPNG | E55: Official via media | F55: https://thedailyguardian.com/business/centre-assures-20-ethanol-blending-target-has-no-impact-on-indias-food-security-or-water-stress20260720183632-739371/
A56: Analysis_Stage4 | B56: PPAC holds no distillery supplier list | C56: CIC order, Jul 2026 (DT Next) | D56: CIC / PPAC | E56: Official via media | F56: https://www.dtnext.in/news/business/cic-directs-petroleum-ministry-arm-to-share-historical-petrol-ethanol-profit-data
A57: Analysis_Stage4 | B57: Punjab farm power subsidy Rs 8,275 crore (2020-21) | C57: Sonker & Kallummal, IIFT working paper 87 (Jul 2025) | D57: IIFT | E57: Institutional | F57: https://wtocentre.iift.ac.in/workingpaper/CWS_WorkingPaper_87_07072025.pdf
A58: Analysis_Stage4 | B58: Forex Rs 1,13,007 crore and crude 193 lakh t to ESY 2023-24 | C58: FIPI Policy & Economic Report, Jan 2025, p.51 | D58: MoPNG / OMC data | E58: Institutional | F58: https://fipi.org.in/Policy_Economic_Report/January25/files/basic-html/page51.html
A59: Analysis_Stage4 | B59: Forex Rs 1,55,000 crore, crude 260 lakh t, CO2 790 lakh t to Oct 2025 | C59: Rajya Sabha reply, Dec 2025 (iamrenew) | D59: MoPNG | E59: Official via media | F59: https://www.iamrenew.com/?p=17662
A60: Analysis_H1 | B60: Maize 380-400 L/t, rice 370-385 L/t | C60: Indian Express, 21 Sep 2026 (SuperKalam summary) | D60: Not named | E60: Media | F60: https://superkalam.com/current-affairs/21-09-2026/ethanol-vision-needs-a-feedstock-reality-check-pg11-98f39b51-e55d-41c4-8088-59beda5efedc
A61: Analysis_H1 | B61: India became a maize importer; competition with poultry feed | C61: The Hindu via Drishti IAS | D61: Not named | E61: Media | F61: https://www.drishtiias.com/daily-updates/daily-news-analysis/india-becomes-net-importer-of-maize/print_manually

Sheet Gaps
A1: Data still missing, and where to get it
A2: Priority A blocks a hypothesis test; B weakens it; C is for Stage 4.
A4: Priority | B4: Missing data | C4: Needed for | D4: Best source | E4: Why not collected | F4: Link
A5: A | B5: State groundwater extraction split by irrigation / industry / domestic | C5: H4 (agriculture's share of depletion) | D5: CGWB National Compilation 2024, Annexure I | E5: Annexure beyond the reader's page limit | F5: https://cgwb.gov.in/cgwbpnm/publication-detail/1326
A6: B | B6: State stage of extraction for 2025 | C6: H4 (latest point) | D6: CGWB National Compilation 2025 | E6: Not yet opened | F6: https://data.opencity.in/dataset/national-compilation-of-dynamic-ground-water-resources-of-india-2025
A7: B | B7: Annual pre- and post-monsoon water levels by state | C7: H4 yearly series | D7: CGWB Ground Water Year Books / India-WRIS | E7: gwdata.cgwb.gov.in in maintenance | F7: https://ckandev.indiadataportal.com/dataset/groundwater
A8: B | B8: Monsoon rainfall 2017, 2023, 2024 by state | C8: H4 rainfall control | D8: IMD end-of-season reports / MoES Parliament answers | E8: Not found as state table yet | F8: https://mausam.imd.gov.in/
A9: B | B9: Ethanol 2019-20 volume; feedstock split 2018-19 to 2022-23; sugar diverted by year; FCI rice actually lifted | C9: H1 series | D9: MoPNG / DFPD Parliament answers; ISMA; FCI annual reports | E9: Scattered across answers | F9: https://sansad.in/
A10: B | B10: Irrigated area by source (tubewell vs canal) by state | C10: H4 groundwater share | D10: DES Land Use Statistics; RBI Handbook Tables 55-56 | E10: RBI new site redirects | F10: https://website.rbi.org.in/web/rbi/-/publications/table-56-state-wise-pattern-of-land-use-net-irrigated-area
A11: B | B11: Distillery capacity by state and feedstock | C11: H1 state allocation | D11: DFPD | E11: Not published as a table found so far | F11: https://dfpd.gov.in/
A12: C | B12: Cost of cultivation and returns per hectare by state | C12: H3 profitability | D12: CACP price policy reports | E12: Stage 3-4 | F12: https://cacp.da.gov.in/
A13: C | B13: Farm electricity subsidy by state; artificial recharge cost per m3 | C13: H5 cost translation | D13: PFC utility performance report; CGWB Master Plan 2020 | E13: Stage 4 | F13: https://cgwb.gov.in/cgwbpnm/public/uploads/documents/168613326251844776file.pdf

Sheet Analysis_H1
A1: H1: share of national output going to ethanol
A2: Feedstock (lakh t) = ethanol (crore L) x 1e7 / litres per tonne / 1e5. Blue cells are inputs; black cells are formulas.
A4: Feedstock | B4: Year | C4: Ethanol low (crore L) | D4: Ethanol high (crore L) | E4: Yield low (L/t) | F4: Yield high (L/t) | G4: Production (lakh t) | H4: Feedstock low (lakh t) | I4: Feedstock high (lakh t) | J4: Share low | K4: Share high
A5: Maize | B5: 2023-24 | C5: 286.47 | D5: 286.47 | E5: 380 | F5: 400 | G5: 376.65 | H5: =C5*10000000/F5/100000 -> 71.6175 | I5: =D5*10000000/E5/100000 -> 75.386842 | J5: =H5/G5 -> 0.19014337 | K5: =I5/G5 -> 0.20015091
A6: Maize | B6: 2024-25 | C6: =0.48*1039 -> 498.72 | D6: =0.51*1039 -> 529.89 | E6: 380 | F6: 400 | G6: 434.09 | H6: =C6*10000000/F6/100000 -> 124.68 | I6: =D6*10000000/E6/100000 -> 139.44474 | J6: =H6/G6 -> 0.28722154 | K6: =I6/G6 -> 0.32123462
A7: Rice and broken grain | B7: 2023-24 | C7: 115.62 | D7: 115.62 | E7: 370 | F7: 470 | G7: 1378.25 | H7: =C7*10000000/F7/100000 -> 24.6 | I7: =D7*10000000/E7/100000 -> 31.248649 | J7: =H7/G7 -> 0.017848721 | K7: =I7/G7 -> 0.0226727
A8: Rice and broken grain | B8: 2024-25 | C8: =718-0.51*1039 -> 188.11 | D8: =718-0.48*1039 -> 219.28 | E8: 370 | F8: 470 | G8: 1501.84 | H8: =C8*10000000/F8/100000 -> 40.023404 | I8: =D8*10000000/E8/100000 -> 59.264865 | J8: =H8/G8 -> 0.026649579 | K8: =I8/G8 -> 0.039461504
A9: Sugarcane (juice route, upper bound) | B9: 2023-24 | C9: 270.27 | D9: 270.27 | E9: 70 | F9: 81 | G9: 4531.58 | H9: =C9*10000000/F9/100000 -> 333.66667 | I9: =D9*10000000/E9/100000 -> 386.1 | J9: =H9/G9 -> 0.073631419 | K9: =I9/G9 -> 0.085202071
A10: Sugarcane (juice route, upper bound) | B10: 2024-25 | C10: 321 | D10: 321 | E10: 70 | F10: 81 | G10: 4546.11 | H10: =C10*10000000/F10/100000 -> 396.2963 | I10: =D10*10000000/E10/100000 -> 458.57143 | J10: =H10/G10 -> 0.087172615 | K10: =I10/G10 -> 0.10087117
A12: Ethanol volumes: 2023-24 Indian Express split; 2024-25 AIDA (grain 718, cane 321 crore L; maize 48-51% of 1,039). Yields: maize 380-400 and rice 370-385 L/t (Indian Express, Sep 2026); rice up to 470 L/t (Kisan Tak); cane juice 70-81 L/t (Jha et al. 2026).
A13: Cane lower bound is 0: ethanol from C-heavy molasses uses no extra cane. Production: DES time series (3rd AE 2025-26).

Sheet Analysis_H2H3
A1: H2 and H3: MSP rise vs output growth, and maize by season
A2: Changes 2015-16 to 2024-25. MSP from MSP_FRP tab; production from National_production tab (linked, green).
A4: Crop | B4: MSP 2015-16 | C4: MSP 2024-25 | D4: MSP rise | E4: Output 2015-16 (lakh t) | F4: Output 2024-25 (lakh t) | G4: Output growth | I4: Rank MSP | J4: Rank output
A5: Rice (paddy MSP) | B5: =MSP_FRP!C5 -> 1410 | C5: =MSP_FRP!L5 -> 2300 | D5: =C5/B5-1 -> 0.63120567 | E5: =National_production!B5 -> 1044.08 | F5: =National_production!B14 -> 1501.84 | G5: =F5/E5-1 -> 0.43843384 | I5: =RANK(D5,$D$5:$D$11,1) -> 3 | J5: =RANK(G5,$G$5:$G$11,1) -> 6
A6: Wheat | B6: =MSP_FRP!C13 -> 1525 | C6: =MSP_FRP!L13 -> 2425 | D6: =C6/B6-1 -> 0.59016393 | E6: =National_production!C5 -> 922.88 | F6: =National_production!C14 -> 1179.45 | G6: =F6/E6-1 -> 0.27801014 | I6: =RANK(D6,$D$5:$D$11,1) -> 2 | J6: =RANK(G6,$G$5:$G$11,1) -> 3
A7: Maize | B7: =MSP_FRP!C6 -> 1325 | C7: =MSP_FRP!L6 -> 2225 | D7: =C7/B7-1 -> 0.67924528 | E7: =National_production!D5 -> 225.67 | F7: =National_production!D14 -> 434.09 | G7: =F7/E7-1 -> 0.92356095 | I7: =RANK(D7,$D$5:$D$11,1) -> 4 | J7: =RANK(G7,$G$5:$G$11,1) -> 7
A8: Jowar | B8: =MSP_FRP!C7 -> 1570 | C8: =MSP_FRP!L7 -> 3371 | D8: =C8/B8-1 -> 1.1471338 | E8: =National_production!E5 -> 42.38 | F8: =National_production!E14 -> 49.55 | G8: =F8/E8-1 -> 0.16918358 | I8: =RANK(D8,$D$5:$D$11,1) -> 6 | J8: =RANK(G8,$G$5:$G$11,1) -> 2
A9: Bajra | B9: =MSP_FRP!C8 -> 1275 | C9: =MSP_FRP!L8 -> 2625 | D9: =C9/B9-1 -> 1.0588235 | E9: =National_production!F5 -> 80.67 | F9: =National_production!F14 -> 112.05 | G9: =F9/E9-1 -> 0.38899219 | I9: =RANK(D9,$D$5:$D$11,1) -> 5 | J9: =RANK(G9,$G$5:$G$11,1) -> 5
A10: Ragi | B10: =MSP_FRP!C9 -> 1650 | C10: =MSP_FRP!L9 -> 4290 | D10: =C10/B10-1 -> 1.6 | E10: =National_production!G5 -> 18.22 | F10: =National_production!G14 -> 19.77 | G10: =F10/E10-1 -> 0.08507135 | I10: =RANK(D10,$D$5:$D$11,1) -> 7 | J10: =RANK(G10,$G$5:$G$11,1) -> 1
A11: Sugarcane (FRP) | B11: =MSP_FRP!C14 -> 230 | C11: =MSP_FRP!L14 -> 340 | D11: =C11/B11-1 -> 0.47826087 | E11: =National_production!H5 -> 3484.48 | F11: =National_production!H14 -> 4546.11 | G11: =F11/E11-1 -> 0.30467387 | I11: =RANK(D11,$D$5:$D$11,1) -> 1 | J11: =RANK(G11,$G$5:$G$11,1) -> 4
A12: Rank correlation, MSP rise vs output growth | D12: =CORREL(I5:I11,J5:J11) -> -0.42857143
A14: All-India maize | B14: Season | C14: 2016-17 | D14: 2017-18 | E14: 2018-19 | F14: 2019-20 | G14: 2020-21 | H14: 2021-22 | I14: 2022-23 | J14: 2023-24 | K14: 2024-25 | L14: 2025-26 | M14: Change 2016-19 avg to 2022-25 avg
A15: Production (lakh t) | B15: Kharif | C15: =SUMIFS(UPAg_crops!$F$2:$F$951,UPAg_crops!$A$2:$A$951,"All India",UPAg_crops!$B$2:$B$951,"Maize",UPAg_crops!$C$2:$C$951,"Kharif",UPAg_crops!$D$2:$D$951,"2016-17") -> 189.19 | D15: =SUMIFS(UPAg_crops!$F$2:$F$951,UPAg_crops!$A$2:$A$951,"All India",UPAg_crops!$B$2:$B$951,"Maize",UPAg_crops!$C$2:$C$951,"Kharif",UPAg_crops!$D$2:$D$951,"2017-18") -> 201.18 | E15: =SUMIFS(UPAg_crops!$F$2:$F$951,UPAg_crops!$A$2:$A$951,"All India",UPAg_crops!$B$2:$B$951,"Maize",UPAg_crops!$C$2:$C$951,"Kharif",UPAg_crops!$D$2:$D$951,"2018-19") -> 194.14 | F15: =SUMIFS(UPAg_crops!$F$2:$F$951,UPAg_crops!$A$2:$A$951,"All India",UPAg_crops!$B$2:$B$951,"Maize",UPAg_crops!$C$2:$C$951,"Kharif",UPAg_crops!$D$2:$D$951,"2019-20") -> 194.29 | G15: =SUMIFS(UPAg_crops!$F$2:$F$951,UPAg_crops!$A$2:$A$951,"All India",UPAg_crops!$B$2:$B$951,"Maize",UPAg_crops!$C$2:$C$951,"Kharif",UPAg_crops!$D$2:$D$951,"2020-21") -> 215.55 | H15: =SUMIFS(UPAg_crops!$F$2:$F$951,UPAg_crops!$A$2:$A$951,"All India",UPAg_crops!$B$2:$B$951,"Maize",UPAg_crops!$C$2:$C$951,"Kharif",UPAg_crops!$D$2:$D$951,"2021-22") -> 226.81 | I15: =SUMIFS(UPAg_crops!$F$2:$F$951,UPAg_crops!$A$2:$A$951,"All India",UPAg_crops!$B$2:$B$951,"Maize",UPAg_crops!$C$2:$C$951,"Kharif",UPAg_crops!$D$2:$D$951,"2022-23") -> 236.74 | J15: =SUMIFS(UPAg_crops!$F$2:$F$951,UPAg_crops!$A$2:$A$951,"All India",UPAg_crops!$B$2:$B$951,"Maize",UPAg_crops!$C$2:$C$951,"Kharif",UPAg_crops!$D$2:$D$951,"2023-24") -> 222.45 | K15: =SUMIFS(UPAg_crops!$F$2:$F$951,UPAg_crops!$A$2:$A$951,"All India",UPAg_crops!$B$2:$B$951,"Maize",UPAg_crops!$C$2:$C$951,"Kharif",UPAg_crops!$D$2:$D$951,"2024-25") -> 248.08 | L15: =SUMIFS(UPAg_crops!$F$2:$F$951,UPAg_crops!$A$2:$A$951,"All India",UPAg_crops!$B$2:$B$951,"Maize",UPAg_crops!$C$2:$C$951,"Kharif",UPAg_crops!$D$2:$D$951,"2025-26") -> 305.09 | M15: =AVERAGE(I15:K15)/AVERAGE(C15:E15)-1 -> 0.21002207
A16: Production (lakh t) | B16: Rabi + Summer | C16: =SUMIFS(UPAg_crops!$F$2:$F$951,UPAg_crops!$A$2:$A$951,"All India",UPAg_crops!$B$2:$B$951,"Maize",UPAg_crops!$C$2:$C$951,"Rabi",UPAg_crops!$D$2:$D$951,"2016-17")+SUMIFS(UPAg_crops!$F$2:$F$951,UPAg_crops!$A$2:$A$951,"All India",UPAg_crops!$B$2:$B$951,"Maize",UPAg_crops!$C$2:$C$951,"Summer",UPAg_crops!$D$2:$D$951,"2016-17") -> 69.81 | D16: =SUMIFS(UPAg_crops!$F$2:$F$951,UPAg_crops!$A$2:$A$951,"All India",UPAg_crops!$B$2:$B$951,"Maize",UPAg_crops!$C$2:$C$951,"Rabi",UPAg_crops!$D$2:$D$951,"2017-18")+SUMIFS(UPAg_crops!$F$2:$F$951,UPAg_crops!$A$2:$A$951,"All India",UPAg_crops!$B$2:$B$951,"Maize",UPAg_crops!$C$2:$C$951,"Summer",UPAg_crops!$D$2:$D$951,"2017-18") -> 86.34 | E16: =SUMIFS(UPAg_crops!$F$2:$F$951,UPAg_crops!$A$2:$A$951,"All India",UPAg_crops!$B$2:$B$951,"Maize",UPAg_crops!$C$2:$C$951,"Rabi",UPAg_crops!$D$2:$D$951,"2018-19")+SUMIFS(UPAg_crops!$F$2:$F$951,UPAg_crops!$A$2:$A$951,"All India",UPAg_crops!$B$2:$B$951,"Maize",UPAg_crops!$C$2:$C$951,"Summer",UPAg_crops!$D$2:$D$951,"2018-19") -> 83.02 | F16: =SUMIFS(UPAg_crops!$F$2:$F$951,UPAg_crops!$A$2:$A$951,"All India",UPAg_crops!$B$2:$B$951,"Maize",UPAg_crops!$C$2:$C$951,"Rabi",UPAg_crops!$D$2:$D$951,"2019-20")+SUMIFS(UPAg_crops!$F$2:$F$951,UPAg_crops!$A$2:$A$951,"All India",UPAg_crops!$B$2:$B$951,"Maize",UPAg_crops!$C$2:$C$951,"Summer",UPAg_crops!$D$2:$D$951,"2019-20") -> 93.37 | G16: =SUMIFS(UPAg_crops!$F$2:$F$951,UPAg_crops!$A$2:$A$951,"All India",UPAg_crops!$B$2:$B$951,"Maize",UPAg_crops!$C$2:$C$951,"Rabi",UPAg_crops!$D$2:$D$951,"2020-21")+SUMIFS(UPAg_crops!$F$2:$F$951,UPAg_crops!$A$2:$A$951,"All India",UPAg_crops!$B$2:$B$951,"Maize",UPAg_crops!$C$2:$C$951,"Summer",UPAg_crops!$D$2:$D$951,"2020-21") -> 100.92 | H16: =SUMIFS(UPAg_crops!$F$2:$F$951,UPAg_crops!$A$2:$A$951,"All India",UPAg_crops!$B$2:$B$951,"Maize",UPAg_crops!$C$2:$C$951,"Rabi",UPAg_crops!$D$2:$D$951,"2021-22")+SUMIFS(UPAg_crops!$F$2:$F$951,UPAg_crops!$A$2:$A$951,"All India",UPAg_crops!$B$2:$B$951,"Maize",UPAg_crops!$C$2:$C$951,"Summer",UPAg_crops!$D$2:$D$951,"2021-22") -> 110.49 | I16: =SUMIFS(UPAg_crops!$F$2:$F$951,UPAg_crops!$A$2:$A$951,"All India",UPAg_crops!$B$2:$B$951,"Maize",UPAg_crops!$C$2:$C$951,"Rabi",UPAg_crops!$D$2:$D$951,"2022-23")+SUMIFS(UPAg_crops!$F$2:$F$951,UPAg_crops!$A$2:$A$951,"All India",UPAg_crops!$B$2:$B$951,"Maize",UPAg_crops!$C$2:$C$951,"Summer",UPAg_crops!$D$2:$D$951,"2022-23") -> 144.11 | J16: =SUMIFS(UPAg_crops!$F$2:$F$951,UPAg_crops!$A$2:$A$951,"All India",UPAg_crops!$B$2:$B$951,"Maize",UPAg_crops!$C$2:$C$951,"Rabi",UPAg_crops!$D$2:$D$951,"2023-24")+SUMIFS(UPAg_crops!$F$2:$F$951,UPAg_crops!$A$2:$A$951,"All India",UPAg_crops!$B$2:$B$951,"Maize",UPAg_crops!$C$2:$C$951,"Summer",UPAg_crops!$D$2:$D$951,"2023-24") -> 154.2 | K16: =SUMIFS(UPAg_crops!$F$2:$F$951,UPAg_crops!$A$2:$A$951,"All India",UPAg_crops!$B$2:$B$951,"Maize",UPAg_crops!$C$2:$C$951,"Rabi",UPAg_crops!$D$2:$D$951,"2024-25")+SUMIFS(UPAg_crops!$F$2:$F$951,UPAg_crops!$A$2:$A$951,"All India",UPAg_crops!$B$2:$B$951,"Maize",UPAg_crops!$C$2:$C$951,"Summer",UPAg_crops!$D$2:$D$951,"2024-25") -> 186 | L16: =SUMIFS(UPAg_crops!$F$2:$F$951,UPAg_crops!$A$2:$A$951,"All India",UPAg_crops!$B$2:$B$951,"Maize",UPAg_crops!$C$2:$C$951,"Rabi",UPAg_crops!$D$2:$D$951,"2025-26")+SUMIFS(UPAg_crops!$F$2:$F$951,UPAg_crops!$A$2:$A$951,"All India",UPAg_crops!$B$2:$B$951,"Maize",UPAg_crops!$C$2:$C$951,"Summer",UPAg_crops!$D$2:$D$951,"2025-26") -> 245.84 | M16: =AVERAGE(I16:K16)/AVERAGE(C16:E16)-1 -> 1.0249613
A17: Area (lakh ha) | B17: Kharif | C17: =SUMIFS(UPAg_crops!$E$2:$E$951,UPAg_crops!$A$2:$A$951,"All India",UPAg_crops!$B$2:$B$951,"Maize",UPAg_crops!$C$2:$C$951,"Kharif",UPAg_crops!$D$2:$D$951,"2016-17") -> 78.42 | D17: =SUMIFS(UPAg_crops!$E$2:$E$951,UPAg_crops!$A$2:$A$951,"All India",UPAg_crops!$B$2:$B$951,"Maize",UPAg_crops!$C$2:$C$951,"Kharif",UPAg_crops!$D$2:$D$951,"2017-18") -> 74.34 | E17: =SUMIFS(UPAg_crops!$E$2:$E$951,UPAg_crops!$A$2:$A$951,"All India",UPAg_crops!$B$2:$B$951,"Maize",UPAg_crops!$C$2:$C$951,"Kharif",UPAg_crops!$D$2:$D$951,"2018-19") -> 73.31 | F17: =SUMIFS(UPAg_crops!$E$2:$E$951,UPAg_crops!$A$2:$A$951,"All India",UPAg_crops!$B$2:$B$951,"Maize",UPAg_crops!$C$2:$C$951,"Kharif",UPAg_crops!$D$2:$D$951,"2019-20") -> 75.53 | G17: =SUMIFS(UPAg_crops!$E$2:$E$951,UPAg_crops!$A$2:$A$951,"All India",UPAg_crops!$B$2:$B$951,"Maize",UPAg_crops!$C$2:$C$951,"Kharif",UPAg_crops!$D$2:$D$951,"2020-21") -> 77.55 | H17: =SUMIFS(UPAg_crops!$E$2:$E$951,UPAg_crops!$A$2:$A$951,"All India",UPAg_crops!$B$2:$B$951,"Maize",UPAg_crops!$C$2:$C$951,"Kharif",UPAg_crops!$D$2:$D$951,"2021-22") -> 77.85 | I17: =SUMIFS(UPAg_crops!$E$2:$E$951,UPAg_crops!$A$2:$A$951,"All India",UPAg_crops!$B$2:$B$951,"Maize",UPAg_crops!$C$2:$C$951,"Kharif",UPAg_crops!$D$2:$D$951,"2022-23") -> 80.53 | J17: =SUMIFS(UPAg_crops!$E$2:$E$951,UPAg_crops!$A$2:$A$951,"All India",UPAg_crops!$B$2:$B$951,"Maize",UPAg_crops!$C$2:$C$951,"Kharif",UPAg_crops!$D$2:$D$951,"2023-24") -> 83.29 | K17: =SUMIFS(UPAg_crops!$E$2:$E$951,UPAg_crops!$A$2:$A$951,"All India",UPAg_crops!$B$2:$B$951,"Maize",UPAg_crops!$C$2:$C$951,"Kharif",UPAg_crops!$D$2:$D$951,"2024-25") -> 84.61 | L17: =SUMIFS(UPAg_crops!$E$2:$E$951,UPAg_crops!$A$2:$A$951,"All India",UPAg_crops!$B$2:$B$951,"Maize",UPAg_crops!$C$2:$C$951,"Kharif",UPAg_crops!$D$2:$D$951,"2025-26") -> 98.61 | M17: =AVERAGE(I17:K17)/AVERAGE(C17:E17)-1 -> 0.098907418
A18: Area (lakh ha) | B18: Rabi + Summer | C18: =SUMIFS(UPAg_crops!$E$2:$E$951,UPAg_crops!$A$2:$A$951,"All India",UPAg_crops!$B$2:$B$951,"Maize",UPAg_crops!$C$2:$C$951,"Rabi",UPAg_crops!$D$2:$D$951,"2016-17")+SUMIFS(UPAg_crops!$E$2:$E$951,UPAg_crops!$A$2:$A$951,"All India",UPAg_crops!$B$2:$B$951,"Maize",UPAg_crops!$C$2:$C$951,"Summer",UPAg_crops!$D$2:$D$951,"2016-17") -> 17.92 | D18: =SUMIFS(UPAg_crops!$E$2:$E$951,UPAg_crops!$A$2:$A$951,"All India",UPAg_crops!$B$2:$B$951,"Maize",UPAg_crops!$C$2:$C$951,"Rabi",UPAg_crops!$D$2:$D$951,"2017-18")+SUMIFS(UPAg_crops!$E$2:$E$951,UPAg_crops!$A$2:$A$951,"All India",UPAg_crops!$B$2:$B$951,"Maize",UPAg_crops!$C$2:$C$951,"Summer",UPAg_crops!$D$2:$D$951,"2017-18") -> 19.46 | E18: =SUMIFS(UPAg_crops!$E$2:$E$951,UPAg_crops!$A$2:$A$951,"All India",UPAg_crops!$B$2:$B$951,"Maize",UPAg_crops!$C$2:$C$951,"Rabi",UPAg_crops!$D$2:$D$951,"2018-19")+SUMIFS(UPAg_crops!$E$2:$E$951,UPAg_crops!$A$2:$A$951,"All India",UPAg_crops!$B$2:$B$951,"Maize",UPAg_crops!$C$2:$C$951,"Summer",UPAg_crops!$D$2:$D$951,"2018-19") -> 16.97 | F18: =SUMIFS(UPAg_crops!$E$2:$E$951,UPAg_crops!$A$2:$A$951,"All India",UPAg_crops!$B$2:$B$951,"Maize",UPAg_crops!$C$2:$C$951,"Rabi",UPAg_crops!$D$2:$D$951,"2019-20")+SUMIFS(UPAg_crops!$E$2:$E$951,UPAg_crops!$A$2:$A$951,"All India",UPAg_crops!$B$2:$B$951,"Maize",UPAg_crops!$C$2:$C$951,"Summer",UPAg_crops!$D$2:$D$951,"2019-20") -> 20.16 | G18: =SUMIFS(UPAg_crops!$E$2:$E$951,UPAg_crops!$A$2:$A$951,"All India",UPAg_crops!$B$2:$B$951,"Maize",UPAg_crops!$C$2:$C$951,"Rabi",UPAg_crops!$D$2:$D$951,"2020-21")+SUMIFS(UPAg_crops!$E$2:$E$951,UPAg_crops!$A$2:$A$951,"All India",UPAg_crops!$B$2:$B$951,"Maize",UPAg_crops!$C$2:$C$951,"Summer",UPAg_crops!$D$2:$D$951,"2020-21") -> 21.37 | H18: =SUMIFS(UPAg_crops!$E$2:$E$951,UPAg_crops!$A$2:$A$951,"All India",UPAg_crops!$B$2:$B$951,"Maize",UPAg_crops!$C$2:$C$951,"Rabi",UPAg_crops!$D$2:$D$951,"2021-22")+SUMIFS(UPAg_crops!$E$2:$E$951,UPAg_crops!$A$2:$A$951,"All India",UPAg_crops!$B$2:$B$951,"Maize",UPAg_crops!$C$2:$C$951,"Summer",UPAg_crops!$D$2:$D$951,"2021-22") -> 21.73 | I18: =SUMIFS(UPAg_crops!$E$2:$E$951,UPAg_crops!$A$2:$A$951,"All India",UPAg_crops!$B$2:$B$951,"Maize",UPAg_crops!$C$2:$C$951,"Rabi",UPAg_crops!$D$2:$D$951,"2022-23")+SUMIFS(UPAg_crops!$E$2:$E$951,UPAg_crops!$A$2:$A$951,"All India",UPAg_crops!$B$2:$B$951,"Maize",UPAg_crops!$C$2:$C$951,"Summer",UPAg_crops!$D$2:$D$951,"2022-23") -> 26.91 | J18: =SUMIFS(UPAg_crops!$E$2:$E$951,UPAg_crops!$A$2:$A$951,"All India",UPAg_crops!$B$2:$B$951,"Maize",UPAg_crops!$C$2:$C$951,"Rabi",UPAg_crops!$D$2:$D$951,"2023-24")+SUMIFS(UPAg_crops!$E$2:$E$951,UPAg_crops!$A$2:$A$951,"All India",UPAg_crops!$B$2:$B$951,"Maize",UPAg_crops!$C$2:$C$951,"Summer",UPAg_crops!$D$2:$D$951,"2023-24") -> 29.12 | K18: =SUMIFS(UPAg_crops!$E$2:$E$951,UPAg_crops!$A$2:$A$951,"All India",UPAg_crops!$B$2:$B$951,"Maize",UPAg_crops!$C$2:$C$951,"Rabi",UPAg_crops!$D$2:$D$951,"2024-25")+SUMIFS(UPAg_crops!$E$2:$E$951,UPAg_crops!$A$2:$A$951,"All India",UPAg_crops!$B$2:$B$951,"Maize",UPAg_crops!$C$2:$C$951,"Summer",UPAg_crops!$D$2:$D$951,"2024-25") -> 36.3 | L18: =SUMIFS(UPAg_crops!$E$2:$E$951,UPAg_crops!$A$2:$A$951,"All India",UPAg_crops!$B$2:$B$951,"Maize",UPAg_crops!$C$2:$C$951,"Rabi",UPAg_crops!$D$2:$D$951,"2025-26")+SUMIFS(UPAg_crops!$E$2:$E$951,UPAg_crops!$A$2:$A$951,"All India",UPAg_crops!$B$2:$B$951,"Maize",UPAg_crops!$C$2:$C$951,"Summer",UPAg_crops!$D$2:$D$951,"2025-26") -> 45.46 | M18: =AVERAGE(I18:K18)/AVERAGE(C18:E18)-1 -> 0.69880405
A19: Rabi + summer share of production | C19: =C16/(C15+C16) -> 0.26953668 | D19: =D16/(D15+D16) -> 0.30029215 | E19: =E16/(E15+E16) -> 0.29953817 | F19: =F16/(F15+F16) -> 0.32458458 | G19: =G16/(G15+G16) -> 0.31889279 | H19: =H16/(H15+H16) -> 0.32757189 | I19: =I16/(I15+I16) -> 0.37839044 | J19: =J16/(J15+J16) -> 0.40939865 | ... L19: =L16/(L15+L16) -> 0.44622729
A21: Maize by season is pulled from the UPAg_crops tab with SUMIFS. 2025-26 = advance estimate.

Sheet Analysis_H4
A1: H4: water-intensive crop expansion vs groundwater change, by state
A2: Crop area = rice + sugarcane + rabi/summer maize (lakh ha), 3-year averages from UPAg_crops. Groundwater from the Groundwater tab (2017 vs 2024).
A4: State | B4: Crop area 2016-19 avg | C4: Crop area 2021-24 avg | D4: Change in crop area | E4: Stage 2017 (%) | F4: Stage 2024 (%) | G4: Change (points) | H4: Extraction change | I4: Resource change | J4: Monsoon departure 2018-22 (avg) | K4: Rank crop | L4: Rank stage | M4: Rank extraction | N4: Rank resource
A5: Bihar | B5: =SUMPRODUCT((UPAg_crops!$A$2:$A$951=$A5)*(((UPAg_crops!$B$2:$B$951="Rice")+(UPAg_crops!$B$2:$B$951="Sugarcane"))*(UPAg_crops!$C$2:$C$951="Total")+(UPAg_crops!$B$2:$B$951="Maize")*((UPAg_crops!$C$2:$C$951="Rabi")+(UPAg_crops!$C$2:$C$951="Summer")))*ISNUMBER(MATCH(UPAg_crops!$D$2:$D$951,{"2016-17","2017-18","2018-19"},0))*UPAg_crops!$E$2:$E$951)/3 -> 39.62 | C5: =SUMPRODUCT((UPAg_crops!$A$2:$A$951=$A5)*(((UPAg_crops!$B$2:$B$951="Rice")+(UPAg_crops!$B$2:$B$951="Sugarcane"))*(UPAg_crops!$C$2:$C$951="Total")+(UPAg_crops!$B$2:$B$951="Maize")*((UPAg_crops!$C$2:$C$951="Rabi")+(UPAg_crops!$C$2:$C$951="Summer")))*ISNUMBER(MATCH(UPAg_crops!$D$2:$D$951,{"2021-22","2022-23","2023-24"},0))*UPAg_crops!$E$2:$E$951)/3 -> 38.276667 | D5: =C5/B5-1 -> -0.033905435 | E5: =Groundwater!B5 -> 45.76 | F5: =Groundwater!F5 -> 45.54 | G5: =F5-E5 -> -0.22 | H5: =Groundwater!F18/Groundwater!B18-1 -> 0.063348416 | I5: =Groundwater!F31/Groundwater!B31-1 -> 0.067609521 | J5: -0.05 | K5: =RANK(D5,$D$5:$D$14,1) -> 1 | L5: =RANK(G5,$G$5:$G$14,1) -> 7 | M5: =RANK(H5,$H$5:$H$14,1) -> 9 | N5: =RANK(I5,$I$5:$I$14,1) -> 7
A6: Haryana | B6: =SUMPRODUCT((UPAg_crops!$A$2:$A$951=$A6)*(((UPAg_crops!$B$2:$B$951="Rice")+(UPAg_crops!$B$2:$B$951="Sugarcane"))*(UPAg_crops!$C$2:$C$951="Total")+(UPAg_crops!$B$2:$B$951="Maize")*((UPAg_crops!$C$2:$C$951="Rabi")+(UPAg_crops!$C$2:$C$951="Summer")))*ISNUMBER(MATCH(UPAg_crops!$D$2:$D$951,{"2016-17","2017-18","2018-19"},0))*UPAg_crops!$E$2:$E$951)/3 -> 15.266667 | C6: =SUMPRODUCT((UPAg_crops!$A$2:$A$951=$A6)*(((UPAg_crops!$B$2:$B$951="Rice")+(UPAg_crops!$B$2:$B$951="Sugarcane"))*(UPAg_crops!$C$2:$C$951="Total")+(UPAg_crops!$B$2:$B$951="Maize")*((UPAg_crops!$C$2:$C$951="Rabi")+(UPAg_crops!$C$2:$C$951="Summer")))*ISNUMBER(MATCH(UPAg_crops!$D$2:$D$951,{"2021-22","2022-23","2023-24"},0))*UPAg_crops!$E$2:$E$951)/3 -> 15.56 | D6: =C6/B6-1 -> 0.019213974 | E6: =Groundwater!B6 -> 136.91 | F6: =Groundwater!F6 -> 135.96 | G6: =F6-E6 -> -0.95 | H6: =Groundwater!F19/Groundwater!B19-1 -> 0.0176 | I6: =Groundwater!F32/Groundwater!B32-1 -> 0.025191676 | J6: -0.044 | K6: =RANK(D6,$D$5:$D$14,1) -> 3 | L6: =RANK(G6,$G$5:$G$14,1) -> 6 | M6: =RANK(H6,$H$5:$H$14,1) -> 5 | N6: =RANK(I6,$I$5:$I$14,1) -> 5
A7: Karnataka | B7: =SUMPRODUCT((UPAg_crops!$A$2:$A$951=$A7)*(((UPAg_crops!$B$2:$B$951="Rice")+(UPAg_crops!$B$2:$B$951="Sugarcane"))*(UPAg_crops!$C$2:$C$951="Total")+(UPAg_crops!$B$2:$B$951="Maize")*((UPAg_crops!$C$2:$C$951="Rabi")+(UPAg_crops!$C$2:$C$951="Summer")))*ISNUMBER(MATCH(UPAg_crops!$D$2:$D$951,{"2016-17","2017-18","2018-19"},0))*UPAg_crops!$E$2:$E$951)/3 -> 15.81 | C7: =SUMPRODUCT((UPAg_crops!$A$2:$A$951=$A7)*(((UPAg_crops!$B$2:$B$951="Rice")+(UPAg_crops!$B$2:$B$951="Sugarcane"))*(UPAg_crops!$C$2:$C$951="Total")+(UPAg_crops!$B$2:$B$951="Maize")*((UPAg_crops!$C$2:$C$951="Rabi")+(UPAg_crops!$C$2:$C$951="Summer")))*ISNUMBER(MATCH(UPAg_crops!$D$2:$D$951,{"2021-22","2022-23","2023-24"},0))*UPAg_crops!$E$2:$E$951)/3 -> 21.016667 | D7: =C7/B7-1 -> 0.32932743 | E7: =Groundwater!B7 -> 69.87 | F7: =Groundwater!F7 -> 68.44 | G7: =F7-E7 -> -1.43 | H7: =Groundwater!F20/Groundwater!B20-1 -> 0.11702128 | I7: =Groundwater!F33/Groundwater!B33-1 -> 0.1413117 | J7: 0.152 | K7: =RANK(D7,$D$5:$D$14,1) -> 9 | L7: =RANK(G7,$G$5:$G$14,1) -> 5 | M7: =RANK(H7,$H$5:$H$14,1) -> 10 | N7: =RANK(I7,$I$5:$I$14,1) -> 9
A8: Madhya Pradesh | B8: =SUMPRODUCT((UPAg_crops!$A$2:$A$951=$A8)*(((UPAg_crops!$B$2:$B$951="Rice")+(UPAg_crops!$B$2:$B$951="Sugarcane"))*(UPAg_crops!$C$2:$C$951="Total")+(UPAg_crops!$B$2:$B$951="Maize")*((UPAg_crops!$C$2:$C$951="Rabi")+(UPAg_crops!$C$2:$C$951="Summer")))*ISNUMBER(MATCH(UPAg_crops!$D$2:$D$951,{"2016-17","2017-18","2018-19"},0))*UPAg_crops!$E$2:$E$951)/3 -> 23.603333 | C8: =SUMPRODUCT((UPAg_crops!$A$2:$A$951=$A8)*(((UPAg_crops!$B$2:$B$951="Rice")+(UPAg_crops!$B$2:$B$951="Sugarcane"))*(UPAg_crops!$C$2:$C$951="Total")+(UPAg_crops!$B$2:$B$951="Maize")*((UPAg_crops!$C$2:$C$951="Rabi")+(UPAg_crops!$C$2:$C$951="Summer")))*ISNUMBER(MATCH(UPAg_crops!$D$2:$D$951,{"2021-22","2022-23","2023-24"},0))*UPAg_crops!$E$2:$E$951)/3 -> 31.053333 | D8: =C8/B8-1 -> 0.31563339 | E8: =Groundwater!B8 -> 54.76 | F8: =Groundwater!F8 -> 58.4 | G8: =F8-E8 -> 3.64 | H8: =Groundwater!F21/Groundwater!B21-1 -> 0.051377119 | I8: =Groundwater!F34/Groundwater!B34-1 -> -0.013925152 | J8: 0.128 | K8: =RANK(D8,$D$5:$D$14,1) -> 8 | L8: =RANK(G8,$G$5:$G$14,1) -> 9 | M8: =RANK(H8,$H$5:$H$14,1) -> 8 | N8: =RANK(I8,$I$5:$I$14,1) -> 3
A9: Maharashtra | B9: =SUMPRODUCT((UPAg_crops!$A$2:$A$951=$A9)*(((UPAg_crops!$B$2:$B$951="Rice")+(UPAg_crops!$B$2:$B$951="Sugarcane"))*(UPAg_crops!$C$2:$C$951="Total")+(UPAg_crops!$B$2:$B$951="Maize")*((UPAg_crops!$C$2:$C$951="Rabi")+(UPAg_crops!$C$2:$C$951="Summer")))*ISNUMBER(MATCH(UPAg_crops!$D$2:$D$951,{"2016-17","2017-18","2018-19"},0))*UPAg_crops!$E$2:$E$951)/3 -> 27.106667 | C9: =SUMPRODUCT((UPAg_crops!$A$2:$A$951=$A9)*(((UPAg_crops!$B$2:$B$951="Rice")+(UPAg_crops!$B$2:$B$951="Sugarcane"))*(UPAg_crops!$C$2:$C$951="Total")+(UPAg_crops!$B$2:$B$951="Maize")*((UPAg_crops!$C$2:$C$951="Rabi")+(UPAg_crops!$C$2:$C$951="Summer")))*ISNUMBER(MATCH(UPAg_crops!$D$2:$D$951,{"2021-22","2022-23","2023-24"},0))*UPAg_crops!$E$2:$E$951)/3 -> 34.81 | D9: =C9/B9-1 -> 0.28418593 | E9: =Groundwater!B9 -> 54.62 | F9: =Groundwater!F9 -> 52.99 | G9: =F9-E9 -> -1.63 | H9: =Groundwater!F22/Groundwater!B22-1 -> 0.010410288 | I9: =Groundwater!F35/Groundwater!B35-1 -> 0.04180602 | J9: 0.164 | K9: =RANK(D9,$D$5:$D$14,1) -> 7 | L9: =RANK(G9,$G$5:$G$14,1) -> 4 | M9: =RANK(H9,$H$5:$H$14,1) -> 3 | N9: =RANK(I9,$I$5:$I$14,1) -> 6
A10: Punjab | B10: =SUMPRODUCT((UPAg_crops!$A$2:$A$951=$A10)*(((UPAg_crops!$B$2:$B$951="Rice")+(UPAg_crops!$B$2:$B$951="Sugarcane"))*(UPAg_crops!$C$2:$C$951="Total")+(UPAg_crops!$B$2:$B$951="Maize")*((UPAg_crops!$C$2:$C$951="Rabi")+(UPAg_crops!$C$2:$C$951="Summer")))*ISNUMBER(MATCH(UPAg_crops!$D$2:$D$951,{"2016-17","2017-18","2018-19"},0))*UPAg_crops!$E$2:$E$951)/3 -> 31.15 | C10: =SUMPRODUCT((UPAg_crops!$A$2:$A$951=$A10)*(((UPAg_crops!$B$2:$B$951="Rice")+(UPAg_crops!$B$2:$B$951="Sugarcane"))*(UPAg_crops!$C$2:$C$951="Total")+(UPAg_crops!$B$2:$B$951="Maize")*((UPAg_crops!$C$2:$C$951="Rabi")+(UPAg_crops!$C$2:$C$951="Summer")))*ISNUMBER(MATCH(UPAg_crops!$D$2:$D$951,{"2021-22","2022-23","2023-24"},0))*UPAg_crops!$E$2:$E$951)/3 -> 31.71 | D10: =C10/B10-1 -> 0.017977528 | E10: =Groundwater!B10 -> 165.77 | F10: =Groundwater!F10 -> 156.87 | G10: =F10-E10 -> -8.9 | H10: =Groundwater!F23/Groundwater!B23-1 -> -0.22694243 | I10: =Groundwater!F36/Groundwater!B36-1 -> -0.18303985 | J10: -0.042 | K10: =RANK(D10,$D$5:$D$14,1) -> 2 | L10: =RANK(G10,$G$5:$G$14,1) -> 2 | M10: =RANK(H10,$H$5:$H$14,1) -> 1 | N10: =RANK(I10,$I$5:$I$14,1) -> 1
A11: Rajasthan | B11: =SUMPRODUCT((UPAg_crops!$A$2:$A$951=$A11)*(((UPAg_crops!$B$2:$B$951="Rice")+(UPAg_crops!$B$2:$B$951="Sugarcane"))*(UPAg_crops!$C$2:$C$951="Total")+(UPAg_crops!$B$2:$B$951="Maize")*((UPAg_crops!$C$2:$C$951="Rabi")+(UPAg_crops!$C$2:$C$951="Summer")))*ISNUMBER(MATCH(UPAg_crops!$D$2:$D$951,{"2016-17","2017-18","2018-19"},0))*UPAg_crops!$E$2:$E$951)/3 -> 2.06 | C11: =SUMPRODUCT((UPAg_crops!$A$2:$A$951=$A11)*(((UPAg_crops!$B$2:$B$951="Rice")+(UPAg_crops!$B$2:$B$951="Sugarcane"))*(UPAg_crops!$C$2:$C$951="Total")+(UPAg_crops!$B$2:$B$951="Maize")*((UPAg_crops!$C$2:$C$951="Rabi")+(UPAg_crops!$C$2:$C$951="Summer")))*ISNUMBER(MATCH(UPAg_crops!$D$2:$D$951,{"2021-22","2022-23","2023-24"},0))*UPAg_crops!$E$2:$E$951)/3 -> 2.5366667 | D11: =C11/B11-1 -> 0.23139159 | E11: =Groundwater!B11 -> 139.88 | F11: =Groundwater!F11 -> 149.86 | G11: =F11-E11 -> 9.98 | H11: =Groundwater!F24/Groundwater!B24-1 -> 0.016696482 | I11: =Groundwater!F37/Groundwater!B37-1 -> -0.051709758 | J11: 0.194 | K11: =RANK(D11,$D$5:$D$14,1) -> 5 | L11: =RANK(G11,$G$5:$G$14,1) -> 10 | M11: =RANK(H11,$H$5:$H$14,1) -> 4 | N11: =RANK(I11,$I$5:$I$14,1) -> 2
A12: Tamil Nadu | B12: =SUMPRODUCT((UPAg_crops!$A$2:$A$951=$A12)*(((UPAg_crops!$B$2:$B$951="Rice")+(UPAg_crops!$B$2:$B$951="Sugarcane"))*(UPAg_crops!$C$2:$C$951="Total")+(UPAg_crops!$B$2:$B$951="Maize")*((UPAg_crops!$C$2:$C$951="Rabi")+(UPAg_crops!$C$2:$C$951="Summer")))*ISNUMBER(MATCH(UPAg_crops!$D$2:$D$951,{"2016-17","2017-18","2018-19"},0))*UPAg_crops!$E$2:$E$951)/3 -> 20.25 | C12: =SUMPRODUCT((UPAg_crops!$A$2:$A$951=$A12)*(((UPAg_crops!$B$2:$B$951="Rice")+(UPAg_crops!$B$2:$B$951="Sugarcane"))*(UPAg_crops!$C$2:$C$951="Total")+(UPAg_crops!$B$2:$B$951="Maize")*((UPAg_crops!$C$2:$C$951="Rabi")+(UPAg_crops!$C$2:$C$951="Summer")))*ISNUMBER(MATCH(UPAg_crops!$D$2:$D$951,{"2021-22","2022-23","2023-24"},0))*UPAg_crops!$E$2:$E$951)/3 -> 25.18 | D12: =C12/B12-1 -> 0.24345679 | E12: =Groundwater!B12 -> 80.94 | F12: =Groundwater!F12 -> 74.26 | G12: =F12-E12 -> -6.68 | H12: =Groundwater!F25/Groundwater!B25-1 -> -0.019008826 | I12: =Groundwater!F38/Groundwater!B38-1 -> 0.069230769 | J12: 0.196 | K12: =RANK(D12,$D$5:$D$14,1) -> 6 | L12: =RANK(G12,$G$5:$G$14,1) -> 3 | M12: =RANK(H12,$H$5:$H$14,1) -> 2 | N12: =RANK(I12,$I$5:$I$14,1) -> 8
A13: Telangana | B13: =SUMPRODUCT((UPAg_crops!$A$2:$A$951=$A13)*(((UPAg_crops!$B$2:$B$951="Rice")+(UPAg_crops!$B$2:$B$951="Sugarcane"))*(UPAg_crops!$C$2:$C$951="Total")+(UPAg_crops!$B$2:$B$951="Maize")*((UPAg_crops!$C$2:$C$951="Rabi")+(UPAg_crops!$C$2:$C$951="Summer")))*ISNUMBER(MATCH(UPAg_crops!$D$2:$D$951,{"2016-17","2017-18","2018-19"},0))*UPAg_crops!$E$2:$E$951)/3 -> 20.433333 | C13: =SUMPRODUCT((UPAg_crops!$A$2:$A$951=$A13)*(((UPAg_crops!$B$2:$B$951="Rice")+(UPAg_crops!$B$2:$B$951="Sugarcane"))*(UPAg_crops!$C$2:$C$951="Total")+(UPAg_crops!$B$2:$B$951="Maize")*((UPAg_crops!$C$2:$C$951="Rabi")+(UPAg_crops!$C$2:$C$951="Summer")))*ISNUMBER(MATCH(UPAg_crops!$D$2:$D$951,{"2021-22","2022-23","2023-24"},0))*UPAg_crops!$E$2:$E$951)/3 -> 45.82 | D13: =C13/B13-1 -> 1.2424144 | E13: =Groundwater!B13 -> 65.45 | F13: =Groundwater!F13 -> 45.91 | G13: =F13-E13 -> -19.54 | H13: =Groundwater!F26/Groundwater!B26-1 -> 0.04697157 | I13: =Groundwater!F39/Groundwater!B39-1 -> 0.49070331 | J13: 0.268 | K13: =RANK(D13,$D$5:$D$14,1) -> 10 | L13: =RANK(G13,$G$5:$G$14,1) -> 1 | M13: =RANK(H13,$H$5:$H$14,1) -> 7 | N13: =RANK(I13,$I$5:$I$14,1) -> 10
A14: Uttar Pradesh | B14: =SUMPRODUCT((UPAg_crops!$A$2:$A$951=$A14)*(((UPAg_crops!$B$2:$B$951="Rice")+(UPAg_crops!$B$2:$B$951="Sugarcane"))*(UPAg_crops!$C$2:$C$951="Total")+(UPAg_crops!$B$2:$B$951="Maize")*((UPAg_crops!$C$2:$C$951="Rabi")+(UPAg_crops!$C$2:$C$951="Summer")))*ISNUMBER(MATCH(UPAg_crops!$D$2:$D$951,{"2016-17","2017-18","2018-19"},0))*UPAg_crops!$E$2:$E$951)/3 -> 81.01 | C14: =SUMPRODUCT((UPAg_crops!$A$2:$A$951=$A14)*(((UPAg_crops!$B$2:$B$951="Rice")+(UPAg_crops!$B$2:$B$951="Sugarcane"))*(UPAg_crops!$C$2:$C$951="Total")+(UPAg_crops!$B$2:$B$951="Maize")*((UPAg_crops!$C$2:$C$951="Rabi")+(UPAg_crops!$C$2:$C$951="Summer")))*ISNUMBER(MATCH(UPAg_crops!$D$2:$D$951,{"2021-22","2022-23","2023-24"},0))*UPAg_crops!$E$2:$E$951)/3 -> 84.583333 | D14: =C14/B14-1 -> 0.044109781 | E14: =Groundwater!B14 -> 70.18 | F14: =Groundwater!F14 -> 70.45 | G14: =F14-E14 -> 0.27 | H14: =Groundwater!F27/Groundwater!B27-1 -> 0.020069808 | I14: =Groundwater!F40/Groundwater!B40-1 -> 0.016227802 | J14: -0.142 | K14: =RANK(D14,$D$5:$D$14,1) -> 4 | L14: =RANK(G14,$G$5:$G$14,1) -> 8 | M14: =RANK(H14,$H$5:$H$14,1) -> 6 | N14: =RANK(I14,$I$5:$I$14,1) -> 4
A16: Spearman: crop vs stage change | D16: =CORREL(K5:K14,L5:L14) -> -0.22424242
A17: Spearman: crop vs extraction change | D17: =CORREL(K5:K14,M5:M14) -> 0.2969697
A18: Spearman: crop vs resource change | D18: =CORREL(K5:K14,N5:N14) -> 0.51515152
A20: With 10 states, |rho| must exceed about 0.65 to be significant at 5%; none does. Rainfall: average of printed monsoon departures 2018-2022 (Rainfall tab sources).
A21: Punjab 2022 discrepancy does not affect this tab (uses 2017 and 2024 only).

Sheet Analysis_Water
A1: Water embedded in ethanol vs national groundwater extraction
A2: bcm = crore L x 1e7 x litres of water per litre / 1e12. Total crop water (rain + irrigation), so these are upper bounds for groundwater.
A4: Water factor (L water per L ethanol)
A5: Maize | B5: 4670 | C5: Kisan Tak / India Today report
A6: Rice and broken grain | B6: 10790 | C6: Food Secretary via Kisan Tak
A7: Cane low | B7: 2000 | C7: ICAR-IISR (commissioned by ISMA)
A8: Cane high | B8: 3630 | C8: Kisan Tak / India Today report
A9: National extraction 2024 (bcm) | B9: 245.646 | C9: RBI Table 107 / CGWB
A11: Year | B11: Maize (crore L, low) | C11: Maize (high) | D11: Grain (low) | E11: Grain (high) | F11: Cane (crore L) | G11: S1 low (bcm) | H11: S1 high (bcm) | I11: S1 share low | J11: S1 share high | K11: S3 low (bcm) | L11: S3 high (bcm) | M11: S3 share low | N11: S3 share high
A12: 2023-24 | B12: 286.47 | C12: 286.47 | D12: 115.62 | E12: 115.62 | F12: 270.27 | G12: =(B12*$B$5+D12*$B$6+F12*$B$7)*10000000/1000000000000 -> 31.258947 | H12: =(C12*$B$5+E12*$B$6+F12*$B$8)*10000000/1000000000000 -> 35.664348 | I12: =G12/$B$9 -> 0.12725201 | J12: =H12/$B$9 -> 0.14518595 | K12: =B12*$B$5*10000000/1000000000000 -> 13.378149 | L12: =(C12*$B$5+F12*$B$8)*10000000/1000000000000 -> 23.18895 | M12: =K12/$B$9 -> 0.05446109 | N12: =L12/$B$9 -> 0.094399868
A13: 2024-25 | B13: =0.48*1039 -> 498.72 | C13: =0.51*1039 -> 529.89 | D13: =718-0.51*1039 -> 188.11 | E13: =718-0.48*1039 -> 219.28 | F13: 321 | G13: =(B13*$B$5+D13*$B$6+F13*$B$7)*10000000/1000000000000 -> 50.007293 | H13: =(C13*$B$5+E13*$B$6+F13*$B$8)*10000000/1000000000000 -> 60.058475 | I13: =G13/$B$9 -> 0.20357463 | J13: =H13/$B$9 -> 0.24449197 | K13: =B13*$B$5*10000000/1000000000000 -> 23.290224 | L13: =(C13*$B$5+F13*$B$8)*10000000/1000000000000 -> 36.398163 | M13: =K13/$B$9 -> 0.094812144 | N13: =L13/$B$9 -> 0.14817324
A15: S1 counts all crop water. S3 drops by-products: surplus FCI rice and C-heavy molasses count as zero; cane counted only if made from juice (high case).
A16: Sanity check: national extraction fell from 248.69 bcm (2017) to 245.65 bcm (2024) while ethanol rose five-fold, so most of this water is not new groundwater pumping.

Sheet Analysis_Stage4
A1: Stage 4: new groundwater from irrigated maize, cost per litre, and a policy scenario
A2: Blue = sourced inputs; black = formulas. Low case uses the low depth and 61% groundwater share; high case uses the high depth and 100%.
A4: Input | B4: Low | C4: High | D4: Unit | E4: Source
A5: Rabi + summer maize area, 2016-19 avg | B5: =(SUMIFS(UPAg_crops!$E$2:$E$951,UPAg_crops!$A$2:$A$951,"All India",UPAg_crops!$B$2:$B$951,"Maize",UPAg_crops!$C$2:$C$951,"Rabi",UPAg_crops!$D$2:$D$951,"2016-17")+SUMIFS(UPAg_crops!$E$2:$E$951,UPAg_crops!$A$2:$A$951,"All India",UPAg_crops!$B$2:$B$951,"Maize",UPAg_crops!$C$2:$C$951,"Rabi",UPAg_crops!$D$2:$D$951,"2017-18")+SUMIFS(UPAg_crops!$E$2:$E$951,UPAg_crops!$A$2:$A$951,"All India",UPAg_crops!$B$2:$B$951,"Maize",UPAg_crops!$C$2:$C$951,"Rabi",UPAg_crops!$D$2:$D$951,"2018-19")+SUMIFS(UPAg_crops!$E$2:$E$951,UPAg_crops!$A$2:$A$951,"All India",UPAg_crops!$B$2:$B$951,"Maize",UPAg_crops!$C$2:$C$951,"Summer",UPAg_crops!$D$2:$D$951,"2016-17")+SUMIFS(UPAg_crops!$E$2:$E$951,UPAg_crops!$A$2:$A$951,"All India",UPAg_crops!$B$2:$B$951,"Maize",UPAg_crops!$C$2:$C$951,"Summer",UPAg_crops!$D$2:$D$951,"2017-18")+SUMIFS(UPAg_crops!$E$2:$E$951,UPAg_crops!$A$2:$A$951,"All India",UPAg_crops!$B$2:$B$951,"Maize",UPAg_crops!$C$2:$C$951,"Summer",UPAg_crops!$D$2:$D$951,"2018-19"))/3 -> 18.116667 | C5: =B5 -> 18.116667 | D5: lakh ha | E5: UPAg_crops (summer reported separately from 2022-23)
A6: Rabi + summer maize area, 2022-25 avg | B6: =(SUMIFS(UPAg_crops!$E$2:$E$951,UPAg_crops!$A$2:$A$951,"All India",UPAg_crops!$B$2:$B$951,"Maize",UPAg_crops!$C$2:$C$951,"Rabi",UPAg_crops!$D$2:$D$951,"2022-23")+SUMIFS(UPAg_crops!$E$2:$E$951,UPAg_crops!$A$2:$A$951,"All India",UPAg_crops!$B$2:$B$951,"Maize",UPAg_crops!$C$2:$C$951,"Rabi",UPAg_crops!$D$2:$D$951,"2023-24")+SUMIFS(UPAg_crops!$E$2:$E$951,UPAg_crops!$A$2:$A$951,"All India",UPAg_crops!$B$2:$B$951,"Maize",UPAg_crops!$C$2:$C$951,"Rabi",UPAg_crops!$D$2:$D$951,"2024-25")+SUMIFS(UPAg_crops!$E$2:$E$951,UPAg_crops!$A$2:$A$951,"All India",UPAg_crops!$B$2:$B$951,"Maize",UPAg_crops!$C$2:$C$951,"Summer",UPAg_crops!$D$2:$D$951,"2022-23")+SUMIFS(UPAg_crops!$E$2:$E$951,UPAg_crops!$A$2:$A$951,"All India",UPAg_crops!$B$2:$B$951,"Maize",UPAg_crops!$C$2:$C$951,"Summer",UPAg_crops!$D$2:$D$951,"2023-24")+SUMIFS(UPAg_crops!$E$2:$E$951,UPAg_crops!$A$2:$A$951,"All India",UPAg_crops!$B$2:$B$951,"Maize",UPAg_crops!$C$2:$C$951,"Summer",UPAg_crops!$D$2:$D$951,"2024-25"))/3 -> 30.776667 | C6: =B6 -> 30.776667 | D6: lakh ha | E6: UPAg_crops
A7: Irrigation depth | B7: 300 | C7: 700 | D7: mm | E7: Low: rabi maize, 5 irrigations x 6 cm (Bharati et al. 2007, Bihar); high: spring/summer maize PET 693-955 mm (Majumder et al. 2016, Punjab)
A8: Groundwater share of irrigation | B8: 0.61 | C8: 1 | D8: fraction | E8: Low: tube wells 45% + other wells 16% of net irrigated area, 2011-12 (MoSPI); high: all from wells
A9: Rabi maize yield 2024-25 | B9: =SUMIFS(UPAg_crops!$F$2:$F$951,UPAg_crops!$A$2:$A$951,"All India",UPAg_crops!$B$2:$B$951,"Maize",UPAg_crops!$C$2:$C$951,"Rabi",UPAg_crops!$D$2:$D$951,"2024-25")/(SUMIFS(UPAg_crops!$E$2:$E$951,UPAg_crops!$A$2:$A$951,"All India",UPAg_crops!$B$2:$B$951,"Maize",UPAg_crops!$C$2:$C$951,"Rabi",UPAg_crops!$D$2:$D$951,"2024-25")) -> 5.3068345 | C9: =B9 -> 5.3068345 | D9: t/ha | E9: UPAg_crops
A10: Summer maize yield 2024-25 | B10: =SUMIFS(UPAg_crops!$F$2:$F$951,UPAg_crops!$A$2:$A$951,"All India",UPAg_crops!$B$2:$B$951,"Maize",UPAg_crops!$C$2:$C$951,"Summer",UPAg_crops!$D$2:$D$951,"2024-25")/(SUMIFS(UPAg_crops!$E$2:$E$951,UPAg_crops!$A$2:$A$951,"All India",UPAg_crops!$B$2:$B$951,"Maize",UPAg_crops!$C$2:$C$951,"Summer",UPAg_crops!$D$2:$D$951,"2024-25")) -> 4.5258824 | C10: =B10 -> 4.5258824 | D10: t/ha | E10: UPAg_crops
A11: Ethanol yield from maize | B11: 380 | C11: 400 | D11: L per t | E11: Indian Express, Sep 2026
A12: Punjab farm power subsidy 2020-21 | B12: 8275 | C12: =B12 -> 8275 | D12: Rs crore | E12: Sonker & Kallummal, IIFT working paper 87
A13: Punjab groundwater extraction 2020 | B13: 33.85 | C13: =B13 -> 33.85 | D13: bcm | E13: RBI Table 107 / CGWB
A14: Forex saved to end ESY 2023-24 | B14: 113007 | C14: =B14 -> 113007 | D14: Rs crore | E14: FIPI Policy & Economic Report, Jan 2025
A15: Forex saved to Oct 2025 | B15: 155000 | C15: =B15 -> 155000 | D15: Rs crore | E15: Rajya Sabha reply, Dec 2025 (iamrenew)
A16: Crude substituted to end ESY 2023-24 | B16: 193 | C16: =B16 -> 193 | D16: lakh t | E16: FIPI, Jan 2025
A17: Crude substituted to Oct 2025 | B17: 260 | C17: =B17 -> 260 | D17: lakh t | E17: Rajya Sabha reply, Dec 2025
A18: Net CO2 reduction to Oct 2025 | B18: 790 | C18: =B18 -> 790 | D18: lakh t | E18: Rajya Sabha reply, Dec 2025
A19: Ethanol blended ESY 2024-25 | B19: 1022.4 | C19: =B19 -> 1022.4 | D19: crore L | E19: PPAC via BioEnergy Times
A20: Maize ethanol price ESY 2023-24 | B20: 71.86 | C20: =B20 -> 71.86 | D20: Rs per L | E20: Lok Sabha AU755
A21: Social cost of carbon (global median, range 177-805) | B21: 417 | C21: =B21 -> 417 | D21: US$ per t CO2 | E21: Ricke et al. 2018
A22: National groundwater extraction 2024 | B22: 245.646 | C22: =B22 -> 245.646 | D22: bcm | E22: RBI Table 107 / CGWB
A23: Summer maize area 2024-25 | B23: =SUMIFS(UPAg_crops!$E$2:$E$951,UPAg_crops!$A$2:$A$951,"All India",UPAg_crops!$B$2:$B$951,"Maize",UPAg_crops!$C$2:$C$951,"Summer",UPAg_crops!$D$2:$D$951,"2024-25") -> 8.5 | C23: =B23 -> 8.5 | D23: lakh ha | E23: UPAg_crops
A24: Summer maize production 2024-25 | B24: =SUMIFS(UPAg_crops!$F$2:$F$951,UPAg_crops!$A$2:$A$951,"All India",UPAg_crops!$B$2:$B$951,"Maize",UPAg_crops!$C$2:$C$951,"Summer",UPAg_crops!$D$2:$D$951,"2024-25") -> 38.47 | C24: =B24 -> 38.47 | D24: lakh t | E24: UPAg_crops
A26: Result | B26: Low | C26: High | D26: Unit | E26: How
A27: New irrigated maize area | B27: =B6-B5 -> 12.66 | C27: =B27 -> 12.66 | D27: lakh ha | E27: post avg - pre avg
A28: New irrigation water | B28: =B27*100000*B7*10/1000000000 -> 3.798 | C28: =C27*100000*C7*10/1000000000 -> 8.862 | D28: bcm per year | E28: area x depth
A29: New groundwater | B29: =B28*B8 -> 2.31678 | C29: =C28*C8 -> 8.862 | D29: bcm per year | E29: irrigation x groundwater share
A30: Share of national extraction | B30: =B29/B22 -> 0.0094313769 | C30: =C29/B22 -> 0.036076305 | D30: %
A31: Groundwater per litre (rabi maize, low; summer maize, high) | B31: =B7*10/B9/C11*B8 -> 0.86209584 | C31: =C7*10/B10/B11*C8 -> 4.0701572 | D31: m3 per L | E31: depth x 10 / yield / ethanol yield x share
A32: Power subsidy per m3 of groundwater (Punjab) | B32: =B12*10000000/(B13*1000000000) -> 2.4446086 | C32: =B32 -> 2.4446086 | D32: Rs per m3 | E32: subsidy / extraction
A33: Water subsidy cost per litre | B33: =B31*B32 -> 2.1074869 | C33: =C31*C32 -> 9.9499412 | D33: Rs per L | E33: groundwater per L x subsidy per m3
A34: Cost as share of maize ethanol price | B34: =B33/B20 -> 0.029327677 | C34: =C33/B20 -> 0.13846286 | D34: %
A35: Forex saved per litre, ESY 2024-25 | B35: =(B15-B14)/B19 -> 41.072966 | C35: =B35 -> 41.072966 | D35: Rs per L | E35: increment / volume
A36: CO2 avoided per litre, ESY 2024-25 | B36: =(B17-B16)*100000*1000/(B19*10000000)*B18/B17 -> 1.9911671 | C36: =B36 -> 1.9911671 | D36: kg per L | E36: crude per L x official CO2/crude ratio
A37: Carbon value per litre at global SCC | B37: =B36/1000*B21 -> 0.83031668 | C37: =C36/1000*B21 -> 0.83031668 | D37: US$ per L | E37: kg/1000 x SCC
A38: P1: groundwater used by summer maize | B38: =B23*100000*C7*10/1000000000*B8 -> 3.6295 | C38: =B23*100000*C7*10/1000000000*C8 -> 5.95 | D38: bcm per year | E38: summer area x high depth x share
A39: P1: ethanol equivalent of summer maize | B39: =B24*100000*B11/10000000 -> 146.186 | C39: =B24*100000*C11/10000000 -> 153.88 | D39: crore L | E39: production x ethanol yield
A41: Power subsidy per m3 is a lower bound on the cost of pumping: it ignores well deepening, energy for non-subsidised pumps and the scarcity value of depleted aquifers.
A42: Maize output rose 12.3 Mt (2016-19 avg to 2022-25 avg), about equal to maize used for ethanol in 2024-25 (12.5-13.9 Mt; Analysis_H1).
A44: Annual power subsidy on new groundwater | B44: =B29*1000000000*B32/10000000 -> 566.36202 | C44: =C29*1000000000*C32/10000000 -> 2166.4121 | D44: Rs crore per year | E44: new groundwater x subsidy per m3
A45: Groundwater per litre, as litres of water | B45: =B31*1000 -> 862.09584 | C45: =C31*1000 -> 4070.1572 | D45: L per L | E45: Compare: distillery process water 3-5 L per L (Rajya Sabha reply, Jul 2026)
A46: P1: power subsidy on summer-maize groundwater | B46: =B38*1000000000*B32/10000000 -> 887.27068 | C46: =C38*1000000000*C32/10000000 -> 1454.5421 | D46: Rs crore per year | E46: P1 groundwater x subsidy per m3
A47: P1: forex saving carried by summer-maize ethanol | B47: =B39*B35 -> 6004.2925 | C47: =C39*C35 -> 6320.3079 | D47: Rs crore per year | E47: P1 ethanol x forex per litre: what would be lost if the volume were cut rather than shifted
A48: P4: water saved if micro-irrigation saves 20-48% | B48: =B29*0.2 -> 0.463356 | C48: =C29*0.48 -> 4.25376 | D48: bcm per year | E48: new groundwater x 20% (low) or 48% (high); Economic Survey 2020-21 via PIB, Aug 2026
A50: Where the new groundwater falls (same low/high cases; extraction from RBI Table 107 / CGWB, entered as values)
A51: State | B51: Rabi+summer maize 2016-19 avg (lakh ha) | C51: 2022-25 avg (lakh ha) | D51: Added area (lakh ha) | E51: New groundwater low (bcm) | F51: New groundwater high (bcm) | G51: Extraction 2017 (bcm) | H51: Extraction 2024 (bcm) | I51: Extraction change (bcm) | J51: Low case / extraction change | K51: High case / 2024 extraction | L51: Stage of extraction 2024
A52: Bihar | B52: =(SUMIFS(UPAg_crops!$E$2:$E$951,UPAg_crops!$A$2:$A$951,"Bihar",UPAg_crops!$B$2:$B$951,"Maize",UPAg_crops!$C$2:$C$951,"Rabi",UPAg_crops!$D$2:$D$951,"2016-17")+SUMIFS(UPAg_crops!$E$2:$E$951,UPAg_crops!$A$2:$A$951,"Bihar",UPAg_crops!$B$2:$B$951,"Maize",UPAg_crops!$C$2:$C$951,"Rabi",UPAg_crops!$D$2:$D$951,"2017-18")+SUMIFS(UPAg_crops!$E$2:$E$951,UPAg_crops!$A$2:$A$951,"Bihar",UPAg_crops!$B$2:$B$951,"Maize",UPAg_crops!$C$2:$C$951,"Rabi",UPAg_crops!$D$2:$D$951,"2018-19")+SUMIFS(UPAg_crops!$E$2:$E$951,UPAg_crops!$A$2:$A$951,"Bihar",UPAg_crops!$B$2:$B$951,"Maize",UPAg_crops!$C$2:$C$951,"Summer",UPAg_crops!$D$2:$D$951,"2016-17")+SUMIFS(UPAg_crops!$E$2:$E$951,UPAg_crops!$A$2:$A$951,"Bihar",UPAg_crops!$B$2:$B$951,"Maize",UPAg_crops!$C$2:$C$951,"Summer",UPAg_crops!$D$2:$D$951,"2017-18")+SUMIFS(UPAg_crops!$E$2:$E$951,UPAg_crops!$A$2:$A$951,"Bihar",UPAg_crops!$B$2:$B$951,"Maize",UPAg_crops!$C$2:$C$951,"Summer",UPAg_crops!$D$2:$D$951,"2018-19"))/3 -> 4.5966667 | C52: =(SUMIFS(UPAg_crops!$E$2:$E$951,UPAg_crops!$A$2:$A$951,"Bihar",UPAg_crops!$B$2:$B$951,"Maize",UPAg_crops!$C$2:$C$951,"Rabi",UPAg_crops!$D$2:$D$951,"2022-23")+SUMIFS(UPAg_crops!$E$2:$E$951,UPAg_crops!$A$2:$A$951,"Bihar",UPAg_crops!$B$2:$B$951,"Maize",UPAg_crops!$C$2:$C$951,"Rabi",UPAg_crops!$D$2:$D$951,"2023-24")+SUMIFS(UPAg_crops!$E$2:$E$951,UPAg_crops!$A$2:$A$951,"Bihar",UPAg_crops!$B$2:$B$951,"Maize",UPAg_crops!$C$2:$C$951,"Rabi",UPAg_crops!$D$2:$D$951,"2024-25")+SUMIFS(UPAg_crops!$E$2:$E$951,UPAg_crops!$A$2:$A$951,"Bihar",UPAg_crops!$B$2:$B$951,"Maize",UPAg_crops!$C$2:$C$951,"Summer",UPAg_crops!$D$2:$D$951,"2022-23")+SUMIFS(UPAg_crops!$E$2:$E$951,UPAg_crops!$A$2:$A$951,"Bihar",UPAg_crops!$B$2:$B$951,"Maize",UPAg_crops!$C$2:$C$951,"Summer",UPAg_crops!$D$2:$D$951,"2023-24")+SUMIFS(UPAg_crops!$E$2:$E$951,UPAg_crops!$A$2:$A$951,"Bihar",UPAg_crops!$B$2:$B$951,"Maize",UPAg_crops!$C$2:$C$951,"Summer",UPAg_crops!$D$2:$D$951,"2024-25"))/3 -> 6.7033333 | D52: =C52-B52 -> 2.1066667 | E52: =D52*100000*B7*10/1000000000*B8 -> 0.38552 | F52: =D52*100000*C7*10/1000000000*C8 -> 1.4746667 | G52: 13.26 | H52: 14.1 | I52: =H52-G52 -> 0.84 | J52: =IF(I52>0,E52/I52,"extraction fell") -> 0.45895238 | K52: =F52/H52 -> 0.10458629 | L52: 0.4554
A53: Karnataka | B53: =(SUMIFS(UPAg_crops!$E$2:$E$951,UPAg_crops!$A$2:$A$951,"Karnataka",UPAg_crops!$B$2:$B$951,"Maize",UPAg_crops!$C$2:$C$951,"Rabi",UPAg_crops!$D$2:$D$951,"2016-17")+SUMIFS(UPAg_crops!$E$2:$E$951,UPAg_crops!$A$2:$A$951,"Karnataka",UPAg_crops!$B$2:$B$951,"Maize",UPAg_crops!$C$2:$C$951,"Rabi",UPAg_crops!$D$2:$D$951,"2017-18")+SUMIFS(UPAg_crops!$E$2:$E$951,UPAg_crops!$A$2:$A$951,"Karnataka",UPAg_crops!$B$2:$B$951,"Maize",UPAg_crops!$C$2:$C$951,"Rabi",UPAg_crops!$D$2:$D$951,"2018-19")+SUMIFS(UPAg_crops!$E$2:$E$951,UPAg_crops!$A$2:$A$951,"Karnataka",UPAg_crops!$B$2:$B$951,"Maize",UPAg_crops!$C$2:$C$951,"Summer",UPAg_crops!$D$2:$D$951,"2016-17")+SUMIFS(UPAg_crops!$E$2:$E$951,UPAg_crops!$A$2:$A$951,"Karnataka",UPAg_crops!$B$2:$B$951,"Maize",UPAg_crops!$C$2:$C$951,"Summer",UPAg_crops!$D$2:$D$951,"2017-18")+SUMIFS(UPAg_crops!$E$2:$E$951,UPAg_crops!$A$2:$A$951,"Karnataka",UPAg_crops!$B$2:$B$951,"Maize",UPAg_crops!$C$2:$C$951,"Summer",UPAg_crops!$D$2:$D$951,"2018-19"))/3 -> 1.13 | C53: =(SUMIFS(UPAg_crops!$E$2:$E$951,UPAg_crops!$A$2:$A$951,"Karnataka",UPAg_crops!$B$2:$B$951,"Maize",UPAg_crops!$C$2:$C$951,"Rabi",UPAg_crops!$D$2:$D$951,"2022-23")+SUMIFS(UPAg_crops!$E$2:$E$951,UPAg_crops!$A$2:$A$951,"Karnataka",UPAg_crops!$B$2:$B$951,"Maize",UPAg_crops!$C$2:$C$951,"Rabi",UPAg_crops!$D$2:$D$951,"2023-24")+SUMIFS(UPAg_crops!$E$2:$E$951,UPAg_crops!$A$2:$A$951,"Karnataka",UPAg_crops!$B$2:$B$951,"Maize",UPAg_crops!$C$2:$C$951,"Rabi",UPAg_crops!$D$2:$D$951,"2024-25")+SUMIFS(UPAg_crops!$E$2:$E$951,UPAg_crops!$A$2:$A$951,"Karnataka",UPAg_crops!$B$2:$B$951,"Maize",UPAg_crops!$C$2:$C$951,"Summer",UPAg_crops!$D$2:$D$951,"2022-23")+SUMIFS(UPAg_crops!$E$2:$E$951,UPAg_crops!$A$2:$A$951,"Karnataka",UPAg_crops!$B$2:$B$951,"Maize",UPAg_crops!$C$2:$C$951,"Summer",UPAg_crops!$D$2:$D$951,"2023-24")+SUMIFS(UPAg_crops!$E$2:$E$951,UPAg_crops!$A$2:$A$951,"Karnataka",UPAg_crops!$B$2:$B$951,"Maize",UPAg_crops!$C$2:$C$951,"Summer",UPAg_crops!$D$2:$D$951,"2024-25"))/3 -> 3.0733333 | D53: =C53-B53 -> 1.9433333 | E53: =D53*100000*B7*10/1000000000*B8 -> 0.35563 | F53: =D53*100000*C7*10/1000000000*C8 -> 1.3603333 | G53: 10.34 | H53: 11.55 | I53: =H53-G53 -> 1.21 | J53: =IF(I53>0,E53/I53,"extraction fell") -> 0.29390909 | K53: =F53/H53 -> 0.11777778 | L53: 0.6844
A54: Uttar Pradesh | B54: =(SUMIFS(UPAg_crops!$E$2:$E$951,UPAg_crops!$A$2:$A$951,"Uttar Pradesh",UPAg_crops!$B$2:$B$951,"Maize",UPAg_crops!$C$2:$C$951,"Rabi",UPAg_crops!$D$2:$D$951,"2016-17")+SUMIFS(UPAg_crops!$E$2:$E$951,UPAg_crops!$A$2:$A$951,"Uttar Pradesh",UPAg_crops!$B$2:$B$951,"Maize",UPAg_crops!$C$2:$C$951,"Rabi",UPAg_crops!$D$2:$D$951,"2017-18")+SUMIFS(UPAg_crops!$E$2:$E$951,UPAg_crops!$A$2:$A$951,"Uttar Pradesh",UPAg_crops!$B$2:$B$951,"Maize",UPAg_crops!$C$2:$C$951,"Rabi",UPAg_crops!$D$2:$D$951,"2018-19")+SUMIFS(UPAg_crops!$E$2:$E$951,UPAg_crops!$A$2:$A$951,"Uttar Pradesh",UPAg_crops!$B$2:$B$951,"Maize",UPAg_crops!$C$2:$C$951,"Summer",UPAg_crops!$D$2:$D$951,"2016-17")+SUMIFS(UPAg_crops!$E$2:$E$951,UPAg_crops!$A$2:$A$951,"Uttar Pradesh",UPAg_crops!$B$2:$B$951,"Maize",UPAg_crops!$C$2:$C$951,"Summer",UPAg_crops!$D$2:$D$951,"2017-18")+SUMIFS(UPAg_crops!$E$2:$E$951,UPAg_crops!$A$2:$A$951,"Uttar Pradesh",UPAg_crops!$B$2:$B$951,"Maize",UPAg_crops!$C$2:$C$951,"Summer",UPAg_crops!$D$2:$D$951,"2018-19"))/3 -> 0.43666667 | C54: =(SUMIFS(UPAg_crops!$E$2:$E$951,UPAg_crops!$A$2:$A$951,"Uttar Pradesh",UPAg_crops!$B$2:$B$951,"Maize",UPAg_crops!$C$2:$C$951,"Rabi",UPAg_crops!$D$2:$D$951,"2022-23")+SUMIFS(UPAg_crops!$E$2:$E$951,UPAg_crops!$A$2:$A$951,"Uttar Pradesh",UPAg_crops!$B$2:$B$951,"Maize",UPAg_crops!$C$2:$C$951,"Rabi",UPAg_crops!$D$2:$D$951,"2023-24")+SUMIFS(UPAg_crops!$E$2:$E$951,UPAg_crops!$A$2:$A$951,"Uttar Pradesh",UPAg_crops!$B$2:$B$951,"Maize",UPAg_crops!$C$2:$C$951,"Rabi",UPAg_crops!$D$2:$D$951,"2024-25")+SUMIFS(UPAg_crops!$E$2:$E$951,UPAg_crops!$A$2:$A$951,"Uttar Pradesh",UPAg_crops!$B$2:$B$951,"Maize",UPAg_crops!$C$2:$C$951,"Summer",UPAg_crops!$D$2:$D$951,"2022-23")+SUMIFS(UPAg_crops!$E$2:$E$951,UPAg_crops!$A$2:$A$951,"Uttar Pradesh",UPAg_crops!$B$2:$B$951,"Maize",UPAg_crops!$C$2:$C$951,"Summer",UPAg_crops!$D$2:$D$951,"2023-24")+SUMIFS(UPAg_crops!$E$2:$E$951,UPAg_crops!$A$2:$A$951,"Uttar Pradesh",UPAg_crops!$B$2:$B$951,"Maize",UPAg_crops!$C$2:$C$951,"Summer",UPAg_crops!$D$2:$D$951,"2024-25"))/3 -> 2.3466667 | D54: =C54-B54 -> 1.91 | E54: =D54*100000*B7*10/1000000000*B8 -> 0.34953 | F54: =D54*100000*C7*10/1000000000*C8 -> 1.337 | G54: 45.84 | H54: 46.76 | I54: =H54-G54 -> 0.92 | J54: =IF(I54>0,E54/I54,"extraction fell") -> 0.37992391 | K54: =F54/H54 -> 0.028592814 | L54: 0.7045
A55: Telangana | B55: =(SUMIFS(UPAg_crops!$E$2:$E$951,UPAg_crops!$A$2:$A$951,"Telangana",UPAg_crops!$B$2:$B$951,"Maize",UPAg_crops!$C$2:$C$951,"Rabi",UPAg_crops!$D$2:$D$951,"2016-17")+SUMIFS(UPAg_crops!$E$2:$E$951,UPAg_crops!$A$2:$A$951,"Telangana",UPAg_crops!$B$2:$B$951,"Maize",UPAg_crops!$C$2:$C$951,"Rabi",UPAg_crops!$D$2:$D$951,"2017-18")+SUMIFS(UPAg_crops!$E$2:$E$951,UPAg_crops!$A$2:$A$951,"Telangana",UPAg_crops!$B$2:$B$951,"Maize",UPAg_crops!$C$2:$C$951,"Rabi",UPAg_crops!$D$2:$D$951,"2018-19")+SUMIFS(UPAg_crops!$E$2:$E$951,UPAg_crops!$A$2:$A$951,"Telangana",UPAg_crops!$B$2:$B$951,"Maize",UPAg_crops!$C$2:$C$951,"Summer",UPAg_crops!$D$2:$D$951,"2016-17")+SUMIFS(UPAg_crops!$E$2:$E$951,UPAg_crops!$A$2:$A$951,"Telangana",UPAg_crops!$B$2:$B$951,"Maize",UPAg_crops!$C$2:$C$951,"Summer",UPAg_crops!$D$2:$D$951,"2017-18")+SUMIFS(UPAg_crops!$E$2:$E$951,UPAg_crops!$A$2:$A$951,"Telangana",UPAg_crops!$B$2:$B$951,"Maize",UPAg_crops!$C$2:$C$951,"Summer",UPAg_crops!$D$2:$D$951,"2018-19"))/3 -> 1.5 | C55: =(SUMIFS(UPAg_crops!$E$2:$E$951,UPAg_crops!$A$2:$A$951,"Telangana",UPAg_crops!$B$2:$B$951,"Maize",UPAg_crops!$C$2:$C$951,"Rabi",UPAg_crops!$D$2:$D$951,"2022-23")+SUMIFS(UPAg_crops!$E$2:$E$951,UPAg_crops!$A$2:$A$951,"Telangana",UPAg_crops!$B$2:$B$951,"Maize",UPAg_crops!$C$2:$C$951,"Rabi",UPAg_crops!$D$2:$D$951,"2023-24")+SUMIFS(UPAg_crops!$E$2:$E$951,UPAg_crops!$A$2:$A$951,"Telangana",UPAg_crops!$B$2:$B$951,"Maize",UPAg_crops!$C$2:$C$951,"Rabi",UPAg_crops!$D$2:$D$951,"2024-25")+SUMIFS(UPAg_crops!$E$2:$E$951,UPAg_crops!$A$2:$A$951,"Telangana",UPAg_crops!$B$2:$B$951,"Maize",UPAg_crops!$C$2:$C$951,"Summer",UPAg_crops!$D$2:$D$951,"2022-23")+SUMIFS(UPAg_crops!$E$2:$E$951,UPAg_crops!$A$2:$A$951,"Telangana",UPAg_crops!$B$2:$B$951,"Maize",UPAg_crops!$C$2:$C$951,"Summer",UPAg_crops!$D$2:$D$951,"2023-24")+SUMIFS(UPAg_crops!$E$2:$E$951,UPAg_crops!$A$2:$A$951,"Telangana",UPAg_crops!$B$2:$B$951,"Maize",UPAg_crops!$C$2:$C$951,"Summer",UPAg_crops!$D$2:$D$951,"2024-25"))/3 -> 3.0166667 | D55: =C55-B55 -> 1.5166667 | E55: =D55*100000*B7*10/1000000000*B8 -> 0.27755 | F55: =D55*100000*C7*10/1000000000*C8 -> 1.0616667 | G55: 8.09 | H55: 8.47 | I55: =H55-G55 -> 0.38 | J55: =IF(I55>0,E55/I55,"extraction fell") -> 0.73039474 | K55: =F55/H55 -> 0.12534435 | L55: 0.4591
A56: Maharashtra | B56: =(SUMIFS(UPAg_crops!$E$2:$E$951,UPAg_crops!$A$2:$A$951,"Maharashtra",UPAg_crops!$B$2:$B$951,"Maize",UPAg_crops!$C$2:$C$951,"Rabi",UPAg_crops!$D$2:$D$951,"2016-17")+SUMIFS(UPAg_crops!$E$2:$E$951,UPAg_crops!$A$2:$A$951,"Maharashtra",UPAg_crops!$B$2:$B$951,"Maize",UPAg_crops!$C$2:$C$951,"Rabi",UPAg_crops!$D$2:$D$951,"2017-18")+SUMIFS(UPAg_crops!$E$2:$E$951,UPAg_crops!$A$2:$A$951,"Maharashtra",UPAg_crops!$B$2:$B$951,"Maize",UPAg_crops!$C$2:$C$951,"Rabi",UPAg_crops!$D$2:$D$951,"2018-19")+SUMIFS(UPAg_crops!$E$2:$E$951,UPAg_crops!$A$2:$A$951,"Maharashtra",UPAg_crops!$B$2:$B$951,"Maize",UPAg_crops!$C$2:$C$951,"Summer",UPAg_crops!$D$2:$D$951,"2016-17")+SUMIFS(UPAg_crops!$E$2:$E$951,UPAg_crops!$A$2:$A$951,"Maharashtra",UPAg_crops!$B$2:$B$951,"Maize",UPAg_crops!$C$2:$C$951,"Summer",UPAg_crops!$D$2:$D$951,"2017-18")+SUMIFS(UPAg_crops!$E$2:$E$951,UPAg_crops!$A$2:$A$951,"Maharashtra",UPAg_crops!$B$2:$B$951,"Maize",UPAg_crops!$C$2:$C$951,"Summer",UPAg_crops!$D$2:$D$951,"2018-19"))/3 -> 3.2766667 | C56: =(SUMIFS(UPAg_crops!$E$2:$E$951,UPAg_crops!$A$2:$A$951,"Maharashtra",UPAg_crops!$B$2:$B$951,"Maize",UPAg_crops!$C$2:$C$951,"Rabi",UPAg_crops!$D$2:$D$951,"2022-23")+SUMIFS(UPAg_crops!$E$2:$E$951,UPAg_crops!$A$2:$A$951,"Maharashtra",UPAg_crops!$B$2:$B$951,"Maize",UPAg_crops!$C$2:$C$951,"Rabi",UPAg_crops!$D$2:$D$951,"2023-24")+SUMIFS(UPAg_crops!$E$2:$E$951,UPAg_crops!$A$2:$A$951,"Maharashtra",UPAg_crops!$B$2:$B$951,"Maize",UPAg_crops!$C$2:$C$951,"Rabi",UPAg_crops!$D$2:$D$951,"2024-25")+SUMIFS(UPAg_crops!$E$2:$E$951,UPAg_crops!$A$2:$A$951,"Maharashtra",UPAg_crops!$B$2:$B$951,"Maize",UPAg_crops!$C$2:$C$951,"Summer",UPAg_crops!$D$2:$D$951,"2022-23")+SUMIFS(UPAg_crops!$E$2:$E$951,UPAg_crops!$A$2:$A$951,"Maharashtra",UPAg_crops!$B$2:$B$951,"Maize",UPAg_crops!$C$2:$C$951,"Summer",UPAg_crops!$D$2:$D$951,"2023-24")+SUMIFS(UPAg_crops!$E$2:$E$951,UPAg_crops!$A$2:$A$951,"Maharashtra",UPAg_crops!$B$2:$B$951,"Maize",UPAg_crops!$C$2:$C$951,"Summer",UPAg_crops!$D$2:$D$951,"2024-25"))/3 -> 4.64 | D56: =C56-B56 -> 1.3633333 | E56: =D56*100000*B7*10/1000000000*B8 -> 0.24949 | F56: =D56*100000*C7*10/1000000000*C8 -> 0.95433333 | G56: 16.33 | H56: 16.5 | I56: =H56-G56 -> 0.17 | J56: =IF(I56>0,E56/I56,"extraction fell") -> 1.4675882 | K56: =F56/H56 -> 0.057838384 | L56: 0.5299
A57: Madhya Pradesh | B57: =(SUMIFS(UPAg_crops!$E$2:$E$951,UPAg_crops!$A$2:$A$951,"Madhya Pradesh",UPAg_crops!$B$2:$B$951,"Maize",UPAg_crops!$C$2:$C$951,"Rabi",UPAg_crops!$D$2:$D$951,"2016-17")+SUMIFS(UPAg_crops!$E$2:$E$951,UPAg_crops!$A$2:$A$951,"Madhya Pradesh",UPAg_crops!$B$2:$B$951,"Maize",UPAg_crops!$C$2:$C$951,"Rabi",UPAg_crops!$D$2:$D$951,"2017-18")+SUMIFS(UPAg_crops!$E$2:$E$951,UPAg_crops!$A$2:$A$951,"Madhya Pradesh",UPAg_crops!$B$2:$B$951,"Maize",UPAg_crops!$C$2:$C$951,"Rabi",UPAg_crops!$D$2:$D$951,"2018-19")+SUMIFS(UPAg_crops!$E$2:$E$951,UPAg_crops!$A$2:$A$951,"Madhya Pradesh",UPAg_crops!$B$2:$B$951,"Maize",UPAg_crops!$C$2:$C$951,"Summer",UPAg_crops!$D$2:$D$951,"2016-17")+SUMIFS(UPAg_crops!$E$2:$E$951,UPAg_crops!$A$2:$A$951,"Madhya Pradesh",UPAg_crops!$B$2:$B$951,"Maize",UPAg_crops!$C$2:$C$951,"Summer",UPAg_crops!$D$2:$D$951,"2017-18")+SUMIFS(UPAg_crops!$E$2:$E$951,UPAg_crops!$A$2:$A$951,"Madhya Pradesh",UPAg_crops!$B$2:$B$951,"Maize",UPAg_crops!$C$2:$C$951,"Summer",UPAg_crops!$D$2:$D$951,"2018-19"))/3 -> 0.22666667 | C57: =(SUMIFS(UPAg_crops!$E$2:$E$951,UPAg_crops!$A$2:$A$951,"Madhya Pradesh",UPAg_crops!$B$2:$B$951,"Maize",UPAg_crops!$C$2:$C$951,"Rabi",UPAg_crops!$D$2:$D$951,"2022-23")+SUMIFS(UPAg_crops!$E$2:$E$951,UPAg_crops!$A$2:$A$951,"Madhya Pradesh",UPAg_crops!$B$2:$B$951,"Maize",UPAg_crops!$C$2:$C$951,"Rabi",UPAg_crops!$D$2:$D$951,"2023-24")+SUMIFS(UPAg_crops!$E$2:$E$951,UPAg_crops!$A$2:$A$951,"Madhya Pradesh",UPAg_crops!$B$2:$B$951,"Maize",UPAg_crops!$C$2:$C$951,"Rabi",UPAg_crops!$D$2:$D$951,"2024-25")+SUMIFS(UPAg_crops!$E$2:$E$951,UPAg_crops!$A$2:$A$951,"Madhya Pradesh",UPAg_crops!$B$2:$B$951,"Maize",UPAg_crops!$C$2:$C$951,"Summer",UPAg_crops!$D$2:$D$951,"2022-23")+SUMIFS(UPAg_crops!$E$2:$E$951,UPAg_crops!$A$2:$A$951,"Madhya Pradesh",UPAg_crops!$B$2:$B$951,"Maize",UPAg_crops!$C$2:$C$951,"Summer",UPAg_crops!$D$2:$D$951,"2023-24")+SUMIFS(UPAg_crops!$E$2:$E$951,UPAg_crops!$A$2:$A$951,"Madhya Pradesh",UPAg_crops!$B$2:$B$951,"Maize",UPAg_crops!$C$2:$C$951,"Summer",UPAg_crops!$D$2:$D$951,"2024-25"))/3 -> 0.79666667 | D57: =C57-B57 -> 0.57 | E57: =D57*100000*B7*10/1000000000*B8 -> 0.10431 | F57: =D57*100000*C7*10/1000000000*C8 -> 0.399 | G57: 18.88 | H57: 19.85 | I57: =H57-G57 -> 0.97 | J57: =IF(I57>0,E57/I57,"extraction fell") -> 0.10753608 | K57: =F57/H57 -> 0.020100756 | L57: 0.584
A58: Tamil Nadu | B58: =(SUMIFS(UPAg_crops!$E$2:$E$951,UPAg_crops!$A$2:$A$951,"Tamil Nadu",UPAg_crops!$B$2:$B$951,"Maize",UPAg_crops!$C$2:$C$951,"Rabi",UPAg_crops!$D$2:$D$951,"2016-17")+SUMIFS(UPAg_crops!$E$2:$E$951,UPAg_crops!$A$2:$A$951,"Tamil Nadu",UPAg_crops!$B$2:$B$951,"Maize",UPAg_crops!$C$2:$C$951,"Rabi",UPAg_crops!$D$2:$D$951,"2017-18")+SUMIFS(UPAg_crops!$E$2:$E$951,UPAg_crops!$A$2:$A$951,"Tamil Nadu",UPAg_crops!$B$2:$B$951,"Maize",UPAg_crops!$C$2:$C$951,"Rabi",UPAg_crops!$D$2:$D$951,"2018-19")+SUMIFS(UPAg_crops!$E$2:$E$951,UPAg_crops!$A$2:$A$951,"Tamil Nadu",UPAg_crops!$B$2:$B$951,"Maize",UPAg_crops!$C$2:$C$951,"Summer",UPAg_crops!$D$2:$D$951,"2016-17")+SUMIFS(UPAg_crops!$E$2:$E$951,UPAg_crops!$A$2:$A$951,"Tamil Nadu",UPAg_crops!$B$2:$B$951,"Maize",UPAg_crops!$C$2:$C$951,"Summer",UPAg_crops!$D$2:$D$951,"2017-18")+SUMIFS(UPAg_crops!$E$2:$E$951,UPAg_crops!$A$2:$A$951,"Tamil Nadu",UPAg_crops!$B$2:$B$951,"Maize",UPAg_crops!$C$2:$C$951,"Summer",UPAg_crops!$D$2:$D$951,"2018-19"))/3 -> 1.7533333 | C58: =(SUMIFS(UPAg_crops!$E$2:$E$951,UPAg_crops!$A$2:$A$951,"Tamil Nadu",UPAg_crops!$B$2:$B$951,"Maize",UPAg_crops!$C$2:$C$951,"Rabi",UPAg_crops!$D$2:$D$951,"2022-23")+SUMIFS(UPAg_crops!$E$2:$E$951,UPAg_crops!$A$2:$A$951,"Tamil Nadu",UPAg_crops!$B$2:$B$951,"Maize",UPAg_crops!$C$2:$C$951,"Rabi",UPAg_crops!$D$2:$D$951,"2023-24")+SUMIFS(UPAg_crops!$E$2:$E$951,UPAg_crops!$A$2:$A$951,"Tamil Nadu",UPAg_crops!$B$2:$B$951,"Maize",UPAg_crops!$C$2:$C$951,"Rabi",UPAg_crops!$D$2:$D$951,"2024-25")+SUMIFS(UPAg_crops!$E$2:$E$951,UPAg_crops!$A$2:$A$951,"Tamil Nadu",UPAg_crops!$B$2:$B$951,"Maize",UPAg_crops!$C$2:$C$951,"Summer",UPAg_crops!$D$2:$D$951,"2022-23")+SUMIFS(UPAg_crops!$E$2:$E$951,UPAg_crops!$A$2:$A$951,"Tamil Nadu",UPAg_crops!$B$2:$B$951,"Maize",UPAg_crops!$C$2:$C$951,"Summer",UPAg_crops!$D$2:$D$951,"2023-24")+SUMIFS(UPAg_crops!$E$2:$E$951,UPAg_crops!$A$2:$A$951,"Tamil Nadu",UPAg_crops!$B$2:$B$951,"Maize",UPAg_crops!$C$2:$C$951,"Summer",UPAg_crops!$D$2:$D$951,"2024-25"))/3 -> 2.2333333 | D58: =C58-B58 -> 0.48 | E58: =D58*100000*B7*10/1000000000*B8 -> 0.08784 | F58: =D58*100000*C7*10/1000000000*C8 -> 0.336 | G58: 14.73 | H58: 14.45 | I58: =H58-G58 -> -0.28 | J58: =IF(I58>0,E58/I58,"extraction fell") -> extraction fell | K58: =F58/H58 -> 0.023252595 | L58: 0.7426
A59: Rajasthan | B59: =(SUMIFS(UPAg_crops!$E$2:$E$951,UPAg_crops!$A$2:$A$951,"Rajasthan",UPAg_crops!$B$2:$B$951,"Maize",UPAg_crops!$C$2:$C$951,"Rabi",UPAg_crops!$D$2:$D$951,"2016-17")+SUMIFS(UPAg_crops!$E$2:$E$951,UPAg_crops!$A$2:$A$951,"Rajasthan",UPAg_crops!$B$2:$B$951,"Maize",UPAg_crops!$C$2:$C$951,"Rabi",UPAg_crops!$D$2:$D$951,"2017-18")+SUMIFS(UPAg_crops!$E$2:$E$951,UPAg_crops!$A$2:$A$951,"Rajasthan",UPAg_crops!$B$2:$B$951,"Maize",UPAg_crops!$C$2:$C$951,"Rabi",UPAg_crops!$D$2:$D$951,"2018-19")+SUMIFS(UPAg_crops!$E$2:$E$951,UPAg_crops!$A$2:$A$951,"Rajasthan",UPAg_crops!$B$2:$B$951,"Maize",UPAg_crops!$C$2:$C$951,"Summer",UPAg_crops!$D$2:$D$951,"2016-17")+SUMIFS(UPAg_crops!$E$2:$E$951,UPAg_crops!$A$2:$A$951,"Rajasthan",UPAg_crops!$B$2:$B$951,"Maize",UPAg_crops!$C$2:$C$951,"Summer",UPAg_crops!$D$2:$D$951,"2017-18")+SUMIFS(UPAg_crops!$E$2:$E$951,UPAg_crops!$A$2:$A$951,"Rajasthan",UPAg_crops!$B$2:$B$951,"Maize",UPAg_crops!$C$2:$C$951,"Summer",UPAg_crops!$D$2:$D$951,"2018-19"))/3 -> 0.046666667 | C59: =(SUMIFS(UPAg_crops!$E$2:$E$951,UPAg_crops!$A$2:$A$951,"Rajasthan",UPAg_crops!$B$2:$B$951,"Maize",UPAg_crops!$C$2:$C$951,"Rabi",UPAg_crops!$D$2:$D$951,"2022-23")+SUMIFS(UPAg_crops!$E$2:$E$951,UPAg_crops!$A$2:$A$951,"Rajasthan",UPAg_crops!$B$2:$B$951,"Maize",UPAg_crops!$C$2:$C$951,"Rabi",UPAg_crops!$D$2:$D$951,"2023-24")+SUMIFS(UPAg_crops!$E$2:$E$951,UPAg_crops!$A$2:$A$951,"Rajasthan",UPAg_crops!$B$2:$B$951,"Maize",UPAg_crops!$C$2:$C$951,"Rabi",UPAg_crops!$D$2:$D$951,"2024-25")+SUMIFS(UPAg_crops!$E$2:$E$951,UPAg_crops!$A$2:$A$951,"Rajasthan",UPAg_crops!$B$2:$B$951,"Maize",UPAg_crops!$C$2:$C$951,"Summer",UPAg_crops!$D$2:$D$951,"2022-23")+SUMIFS(UPAg_crops!$E$2:$E$951,UPAg_crops!$A$2:$A$951,"Rajasthan",UPAg_crops!$B$2:$B$951,"Maize",UPAg_crops!$C$2:$C$951,"Summer",UPAg_crops!$D$2:$D$951,"2023-24")+SUMIFS(UPAg_crops!$E$2:$E$951,UPAg_crops!$A$2:$A$951,"Rajasthan",UPAg_crops!$B$2:$B$951,"Maize",UPAg_crops!$C$2:$C$951,"Summer",UPAg_crops!$D$2:$D$951,"2024-25"))/3 -> 0.24 | D59: =C59-B59 -> 0.19333333 | E59: =D59*100000*B7*10/1000000000*B8 -> 0.03538 | F59: =D59*100000*C7*10/1000000000*C8 -> 0.13533333 | G59: 16.77 | H59: 17.05 | I59: =H59-G59 -> 0.28 | J59: =IF(I59>0,E59/I59,"extraction fell") -> 0.12635714 | K59: =F59/H59 -> 0.0079374389 | L59: 1.4986
A61: Gross figures: some new rabi maize replaced other rabi crops (wheat, pulses) that also used water, and not all of it went to ethanol. State averages hide block-level over-exploitation.

Sheet README
A1: NeerNexus Stage 2 dataset: E20, crops, groundwater, rainfall and prices
A3: Purpose | B3: Data for testing H1-H5 (see Stage 1 doc). Every number traces to the Source_Log tab.
A4: States | B4: Bihar, Haryana, Karnataka, Madhya Pradesh, Maharashtra, Punjab, Rajasthan, Tamil Nadu, Telangana, Uttar Pradesh, plus All India.
A5: Period | B5: 2015-16 to 2024-25 where available. Groundwater stage of extraction only exists for 2017, 2020, 2022, 2023, 2024 (CGWB).
A6: Accessed | B6: All sources opened on 25 Oct 2026.
A7: Formulas | B7: Cells in black on white with a formula recompute (growth rates, cross-checks). Yellow cells mark gaps still to fill.
A8: Status | B8: Collected: groundwater, state crop area and production 2016-17 to 2025-26 for maize (by season), rice, sugarcane, wheat, jowar, bajra, ragi (UPAg), national production, MSP/FRP, monsoon rainfall (7 of 10 years), national ethanol series.
A9: Analysis | B9: Stage 3 tabs: Analysis_H1 (ethanol share of crops), Analysis_H2H3 (MSP vs output), Analysis_H4 (crop expansion vs groundwater, rank correlations), Analysis_Water (embedded water scenarios). Stage 4 tab: Analysis_Stage4 (new groundwater from irrigated maize, cost per litre, state distribution, summer-maize policy scenario). All computed with formulas.
A10: Status | B10: Missing: groundwater use split by state, water levels, 3 rainfall years, irrigated area by source. See Gaps tab.
A11: Conflicts | B11: Where two credible sources disagree, both are kept and flagged in a Note column; see Source_Log.
A12: Units | B12: Area: thousand hectares ('000 ha) unless stated. Production: thousand tonnes ('000 t) unless stated. Water: billion cubic metres (bcm). Rainfall: mm. Prices: Rs per quintal or Rs per litre.
